{
"meta":{"test_sets":[],"test_metrics":[],"learn_metrics":[{"best_value":"Min","name":"RMSE"}],"launch_mode":"Train","parameters":"","iteration_count":1000,"learn_sets":["learn"],"name":"experiment"},
"iterations":[
{"learn":[14.59871775],"iteration":0,"passed_time":0.04877945773,"remaining_time":48.73067827},
{"learn":[14.22518863],"iteration":1,"passed_time":0.04969851602,"remaining_time":24.79955949},
{"learn":[13.8866124],"iteration":2,"passed_time":0.05058713503,"remaining_time":16.81179121},
{"learn":[13.52356875],"iteration":3,"passed_time":0.05152458288,"remaining_time":12.82962114},
{"learn":[13.18870211],"iteration":4,"passed_time":0.05252534924,"remaining_time":10.4525445},
{"learn":[12.9124226],"iteration":5,"passed_time":0.0532340525,"remaining_time":8.819108031},
{"learn":[12.60003351],"iteration":6,"passed_time":0.0537718898,"remaining_time":7.627926653},
{"learn":[12.32990573],"iteration":7,"passed_time":0.05433378652,"remaining_time":6.737389529},
{"learn":[12.0660619],"iteration":8,"passed_time":0.05492169264,"remaining_time":6.0474886},
{"learn":[11.77309809],"iteration":9,"passed_time":0.05544891018,"remaining_time":5.489442108},
{"learn":[11.49227636],"iteration":10,"passed_time":0.05598862743,"remaining_time":5.033886594},
{"learn":[11.26264833],"iteration":11,"passed_time":0.05648880562,"remaining_time":4.650911663},
{"learn":[11.04260393],"iteration":12,"passed_time":0.05700496343,"remaining_time":4.327992223},
{"learn":[10.79916926],"iteration":13,"passed_time":0.05747073242,"remaining_time":4.047581584},
{"learn":[10.5541002],"iteration":14,"passed_time":0.05791355196,"remaining_time":3.802989912},
{"learn":[10.31918115],"iteration":15,"passed_time":0.05835191161,"remaining_time":3.588642564},
{"learn":[10.10004441],"iteration":16,"passed_time":0.05949691456,"remaining_time":3.440321589},
{"learn":[9.894556723],"iteration":17,"passed_time":0.06014062936,"remaining_time":3.281005446},
{"learn":[9.690174082],"iteration":18,"passed_time":0.06080578364,"remaining_time":3.139498619},
{"learn":[9.506034866],"iteration":19,"passed_time":0.06128339236,"remaining_time":3.002886226},
{"learn":[9.338524633],"iteration":20,"passed_time":0.0617009725,"remaining_time":2.876440575},
{"learn":[9.170203312],"iteration":21,"passed_time":0.0621624516,"remaining_time":2.76340353},
{"learn":[9.010299969],"iteration":22,"passed_time":0.06265438998,"remaining_time":2.661449522},
{"learn":[8.843866678],"iteration":23,"passed_time":0.06314347842,"remaining_time":2.567834789},
{"learn":[8.690548059],"iteration":24,"passed_time":0.06357710818,"remaining_time":2.479507219},
{"learn":[8.555307687],"iteration":25,"passed_time":0.06412326528,"remaining_time":2.402156168},
{"learn":[8.413851302],"iteration":26,"passed_time":0.06454235538,"remaining_time":2.325915251},
{"learn":[8.29256019],"iteration":27,"passed_time":0.06496071549,"remaining_time":2.255064838},
{"learn":[8.162193833],"iteration":28,"passed_time":0.06531273718,"remaining_time":2.186850614},
{"learn":[8.040736294],"iteration":29,"passed_time":0.06569419817,"remaining_time":2.124112407},
{"learn":[7.921220278],"iteration":30,"passed_time":0.06610481847,"remaining_time":2.066308681},
{"learn":[7.809589039],"iteration":31,"passed_time":0.06652594852,"remaining_time":2.012409943},
{"learn":[7.699675801],"iteration":32,"passed_time":0.06696072825,"remaining_time":1.962152249},
{"learn":[7.60645267],"iteration":33,"passed_time":0.06739862791,"remaining_time":1.914913958},
{"learn":[7.498880302],"iteration":34,"passed_time":0.06791268576,"remaining_time":1.872449765},
{"learn":[7.401158744],"iteration":35,"passed_time":0.06843090352,"remaining_time":1.832427528},
{"learn":[7.306431077],"iteration":36,"passed_time":0.06893844153,"remaining_time":1.794262681},
{"learn":[7.223863468],"iteration":37,"passed_time":0.06940045062,"remaining_time":1.756927197},
{"learn":[7.143477682],"iteration":38,"passed_time":0.06987903931,"remaining_time":1.7218912},
{"learn":[7.062817131],"iteration":39,"passed_time":0.07026868011,"remaining_time":1.686448323},
{"learn":[6.990793435],"iteration":40,"passed_time":0.071331765,"remaining_time":1.668467381},
{"learn":[6.931862224],"iteration":41,"passed_time":0.07175024511,"remaining_time":1.636588924},
{"learn":[6.858296558],"iteration":42,"passed_time":0.07323304009,"remaining_time":1.629860915},
{"learn":[6.786268161],"iteration":43,"passed_time":0.07375362779,"remaining_time":1.602465186},
{"learn":[6.717118549],"iteration":44,"passed_time":0.07424194625,"remaining_time":1.575579082},
{"learn":[6.652948106],"iteration":45,"passed_time":0.07473858452,"remaining_time":1.550013253},
{"learn":[6.589686076],"iteration":46,"passed_time":0.07518111407,"remaining_time":1.524417058},
{"learn":[6.531283097],"iteration":47,"passed_time":0.07558951442,"remaining_time":1.499192036},
{"learn":[6.471368031],"iteration":48,"passed_time":0.07603302394,"remaining_time":1.475661342},
{"learn":[6.416481395],"iteration":49,"passed_time":0.07646403376,"remaining_time":1.452816641},
{"learn":[6.369870822],"iteration":50,"passed_time":0.07694392243,"remaining_time":1.431760439},
{"learn":[6.325678067],"iteration":51,"passed_time":0.07736305253,"remaining_time":1.410387958},
{"learn":[6.275766122],"iteration":52,"passed_time":0.07781252191,"remaining_time":1.390348269},
{"learn":[6.224773967],"iteration":53,"passed_time":0.07819231294,"remaining_time":1.369813482},
{"learn":[6.182249254],"iteration":54,"passed_time":0.07860743313,"remaining_time":1.350618624},
{"learn":[6.139904173],"iteration":55,"passed_time":0.07900390377,"remaining_time":1.331780092},
{"learn":[6.100525536],"iteration":56,"passed_time":0.07938041487,"remaining_time":1.313258443},
{"learn":[6.062568564],"iteration":57,"passed_time":0.07981472461,"remaining_time":1.296301217},
{"learn":[6.030559288],"iteration":58,"passed_time":0.08028321355,"remaining_time":1.280449219},
{"learn":[5.997931376],"iteration":59,"passed_time":0.08078542168,"remaining_time":1.265638273},
{"learn":[5.964103835],"iteration":60,"passed_time":0.08123251112,"remaining_time":1.250447999},
{"learn":[5.933729724],"iteration":61,"passed_time":0.08166003102,"remaining_time":1.235437244},
{"learn":[5.901932711],"iteration":62,"passed_time":0.08214391959,"remaining_time":1.22172782},
{"learn":[5.873727795],"iteration":63,"passed_time":0.08256413967,"remaining_time":1.207500543},
{"learn":[5.846485734],"iteration":64,"passed_time":0.08300633922,"remaining_time":1.194014264},
{"learn":[5.820630862],"iteration":65,"passed_time":0.0834049298,"remaining_time":1.180306128},
{"learn":[5.793646238],"iteration":66,"passed_time":0.08377267112,"remaining_time":1.166565704},
{"learn":[5.765388646],"iteration":67,"passed_time":0.08413387259,"remaining_time":1.15312896},
{"learn":[5.747073912],"iteration":68,"passed_time":0.08449276411,"remaining_time":1.140040049},
{"learn":[5.722315217],"iteration":69,"passed_time":0.0848487957,"remaining_time":1.127276857},
{"learn":[5.699970599],"iteration":70,"passed_time":0.08520113737,"remaining_time":1.114814882},
{"learn":[5.682732647],"iteration":71,"passed_time":0.08558272836,"remaining_time":1.103066277},
{"learn":[5.663525791],"iteration":72,"passed_time":0.08595387959,"remaining_time":1.091496526},
{"learn":[5.642381613],"iteration":73,"passed_time":0.08639750911,"remaining_time":1.081136398},
{"learn":[5.621404779],"iteration":74,"passed_time":0.08678083006,"remaining_time":1.070296904},
{"learn":[5.602460129],"iteration":75,"passed_time":0.08714366149,"remaining_time":1.059483463},
{"learn":[5.587337574],"iteration":76,"passed_time":0.08754619198,"remaining_time":1.04941734},
{"learn":[5.572393026],"iteration":77,"passed_time":0.08807140957,"remaining_time":1.041049226},
{"learn":[5.558425806],"iteration":78,"passed_time":0.08850289938,"remaining_time":1.031786966},
{"learn":[5.541518902],"iteration":79,"passed_time":0.08901388731,"remaining_time":1.023659704},
{"learn":[5.526157283],"iteration":80,"passed_time":0.08943548735,"remaining_time":1.014706332},
{"learn":[5.511746977],"iteration":81,"passed_time":0.0898821568,"remaining_time":1.006241707},
{"learn":[5.504975022],"iteration":82,"passed_time":0.09009317181,"remaining_time":0.9953667296},
{"learn":[5.493980522],"iteration":83,"passed_time":0.09064988866,"remaining_time":0.9885154526},
{"learn":[5.480745463],"iteration":84,"passed_time":0.09116186657,"remaining_time":0.9813306813},
{"learn":[5.464052013],"iteration":85,"passed_time":0.09155451729,"remaining_time":0.9730328931},
{"learn":[5.449143727],"iteration":86,"passed_time":0.09190373905,"remaining_time":0.9644610776},
{"learn":[5.438255432],"iteration":87,"passed_time":0.09227074038,"remaining_time":0.9562604003},
{"learn":[5.425927931],"iteration":88,"passed_time":0.09267443084,"remaining_time":0.9486113089},
{"learn":[5.412331217],"iteration":89,"passed_time":0.09310301072,"remaining_time":0.9413748861},
{"learn":[5.400691499],"iteration":90,"passed_time":0.09350388125,"remaining_time":0.9340112973},
{"learn":[5.391618744],"iteration":91,"passed_time":0.09387864239,"remaining_time":0.9265413836},
{"learn":[5.380766572],"iteration":92,"passed_time":0.09424945363,"remaining_time":0.9191855317},
{"learn":[5.372207183],"iteration":93,"passed_time":0.09465804398,"remaining_time":0.9123424239},
{"learn":[5.362918837],"iteration":94,"passed_time":0.09507276419,"remaining_time":0.9056931746},
{"learn":[5.348292324],"iteration":95,"passed_time":0.0955294134,"remaining_time":0.8995686428},
{"learn":[5.339772295],"iteration":96,"passed_time":0.09593719377,"remaining_time":0.8931060409},
{"learn":[5.331515983],"iteration":97,"passed_time":0.09637235349,"remaining_time":0.8870190086},
{"learn":[5.323861644],"iteration":98,"passed_time":0.09680495327,"remaining_time":0.8810228575},
{"learn":[5.313277281],"iteration":99,"passed_time":0.09721460359,"remaining_time":0.8749314323},
{"learn":[5.30685627],"iteration":100,"passed_time":0.09762942379,"remaining_time":0.8689985346},
{"learn":[5.29652059],"iteration":101,"passed_time":0.09800640489,"remaining_time":0.8628407019},
{"learn":[5.288350766],"iteration":102,"passed_time":0.09837589616,"remaining_time":0.8567298918},
{"learn":[5.27993346],"iteration":103,"passed_time":0.0987595571,"remaining_time":0.8508515688},
{"learn":[5.271789139],"iteration":104,"passed_time":0.09913893814,"remaining_time":0.8450414251},
{"learn":[5.262684686],"iteration":105,"passed_time":0.09953368881,"remaining_time":0.8394633754},
{"learn":[5.251619772],"iteration":106,"passed_time":0.09993066943,"remaining_time":0.8340008206},
{"learn":[5.241012171],"iteration":107,"passed_time":0.1002910209,"remaining_time":0.8283295432},
{"learn":[5.232684032],"iteration":108,"passed_time":0.1006453626,"remaining_time":0.8227065875},
{"learn":[5.224267141],"iteration":109,"passed_time":0.1010217137,"remaining_time":0.8173575014},
{"learn":[5.216324968],"iteration":110,"passed_time":0.1013951848,"remaining_time":0.8120749488},
{"learn":[5.211102527],"iteration":111,"passed_time":0.1018153049,"remaining_time":0.8072499175},
{"learn":[5.206364257],"iteration":112,"passed_time":0.1022659543,"remaining_time":0.8027424906},
{"learn":[5.196937641],"iteration":113,"passed_time":0.1027351032,"remaining_time":0.7984500125},
{"learn":[5.190746047],"iteration":114,"passed_time":0.103165653,"remaining_time":0.7939269819},
{"learn":[5.181885213],"iteration":115,"passed_time":0.1035633036,"remaining_time":0.7892237966},
{"learn":[5.178293568],"iteration":116,"passed_time":0.1039150453,"remaining_time":0.7842477351},
{"learn":[5.170991438],"iteration":117,"passed_time":0.1043829143,"remaining_time":0.7802180541},
{"learn":[5.166257212],"iteration":118,"passed_time":0.1048742627,"remaining_time":0.7764220622},
{"learn":[5.161421246],"iteration":119,"passed_time":0.1053012426,"remaining_time":0.7722091122},
{"learn":[5.158223542],"iteration":120,"passed_time":0.1056998232,"remaining_time":0.7678524343},
{"learn":[5.15470988],"iteration":121,"passed_time":0.1059927762,"remaining_time":0.7628004716},
{"learn":[5.146388143],"iteration":122,"passed_time":0.1063775771,"remaining_time":0.7584807736},
{"learn":[5.139529364],"iteration":123,"passed_time":0.1068272865,"remaining_time":0.7546830886},
{"learn":[5.134276023],"iteration":124,"passed_time":0.1072849657,"remaining_time":0.75099476},
{"learn":[5.128536065],"iteration":125,"passed_time":0.1078345627,"remaining_time":0.7479953002},
{"learn":[5.123300353],"iteration":126,"passed_time":0.1082259835,"remaining_time":0.7439471148},
{"learn":[5.116200518],"iteration":127,"passed_time":0.1087318315,"remaining_time":0.7407356023},
{"learn":[5.108728704],"iteration":128,"passed_time":0.1092468894,"remaining_time":0.737628222},
{"learn":[5.104075866],"iteration":129,"passed_time":0.1096664595,"remaining_time":0.7339216902},
{"learn":[5.100317606],"iteration":130,"passed_time":0.110022911,"remaining_time":0.7298466388},
{"learn":[5.095814182],"iteration":131,"passed_time":0.1103824125,"remaining_time":0.7258479855},
{"learn":[5.092146915],"iteration":132,"passed_time":0.110743964,"remaining_time":0.7219174195},
{"learn":[5.085258329],"iteration":133,"passed_time":0.1111207851,"remaining_time":0.7181388052},
{"learn":[5.079219421],"iteration":134,"passed_time":0.1115381052,"remaining_time":0.7146700817},
{"learn":[5.076476829],"iteration":135,"passed_time":0.1119220062,"remaining_time":0.7110339216},
{"learn":[5.072133867],"iteration":136,"passed_time":0.1123326865,"remaining_time":0.7076139301},
{"learn":[5.067031564],"iteration":137,"passed_time":0.1127474467,"remaining_time":0.7042630365},
{"learn":[5.061358312],"iteration":138,"passed_time":0.113159027,"remaining_time":0.7009346921},
{"learn":[5.056759124],"iteration":139,"passed_time":0.1135273083,"remaining_time":0.6973820364},
{"learn":[5.050254],"iteration":140,"passed_time":0.1139513582,"remaining_time":0.694214303},
{"learn":[5.048376474],"iteration":141,"passed_time":0.1142190619,"remaining_time":0.690140529},
{"learn":[5.042603751],"iteration":142,"passed_time":0.1146591915,"remaining_time":0.6871533366},
{"learn":[5.037477349],"iteration":143,"passed_time":0.1150729317,"remaining_time":0.6840446498},
{"learn":[5.03230489],"iteration":144,"passed_time":0.1154996817,"remaining_time":0.681049847},
{"learn":[5.025976187],"iteration":145,"passed_time":0.1159175618,"remaining_time":0.6780383409},
{"learn":[5.01952451],"iteration":146,"passed_time":0.1163961005,"remaining_time":0.6754141069},
{"learn":[5.017569424],"iteration":147,"passed_time":0.1168068008,"remaining_time":0.6724283396},
{"learn":[5.008962367],"iteration":148,"passed_time":0.1172902894,"remaining_time":0.6698928607},
{"learn":[5.003880266],"iteration":149,"passed_time":0.1177173093,"remaining_time":0.6670647526},
{"learn":[4.996387564],"iteration":150,"passed_time":0.1182699062,"remaining_time":0.6649745058},
{"learn":[4.993361683],"iteration":151,"passed_time":0.1187237555,"remaining_time":0.6623535833},
{"learn":[4.99005752],"iteration":152,"passed_time":0.1192049741,"remaining_time":0.6599125039},
{"learn":[4.986908764],"iteration":153,"passed_time":0.1195955249,"remaining_time":0.6569987927},
{"learn":[4.985207175],"iteration":154,"passed_time":0.1199767359,"remaining_time":0.6540667215},
{"learn":[4.979003494],"iteration":155,"passed_time":0.1203648267,"remaining_time":0.6512045754},
{"learn":[4.973142217],"iteration":156,"passed_time":0.1207663973,"remaining_time":0.6484463241},
{"learn":[4.967056696],"iteration":157,"passed_time":0.1212145567,"remaining_time":0.6459661817},
{"learn":[4.961460696],"iteration":158,"passed_time":0.1216949653,"remaining_time":0.643682175},
{"learn":[4.954240363],"iteration":159,"passed_time":0.1222462923,"remaining_time":0.6417930345},
{"learn":[4.952320707],"iteration":160,"passed_time":0.1225235157,"remaining_time":0.63849211},
{"learn":[4.948337777],"iteration":161,"passed_time":0.1229462858,"remaining_time":0.6359814041},
{"learn":[4.943228639],"iteration":162,"passed_time":0.1233497462,"remaining_time":0.6333971631},
{"learn":[4.938545759],"iteration":163,"passed_time":0.1237336472,"remaining_time":0.6307398111},
{"learn":[4.935330572],"iteration":164,"passed_time":0.124119698,"remaining_time":0.6281208961},
{"learn":[4.932051543],"iteration":165,"passed_time":0.1245142787,"remaining_time":0.6255717377},
{"learn":[4.928964153],"iteration":166,"passed_time":0.1249048095,"remaining_time":0.6230281815},
{"learn":[4.922860227],"iteration":167,"passed_time":0.1252949603,"remaining_time":0.6205083747},
{"learn":[4.917668772],"iteration":168,"passed_time":0.125688381,"remaining_time":0.6180298497},
{"learn":[4.910365386],"iteration":169,"passed_time":0.1261053811,"remaining_time":0.6156909785},
{"learn":[4.906457206],"iteration":170,"passed_time":0.1265203013,"remaining_time":0.6133645018},
{"learn":[4.901996508],"iteration":171,"passed_time":0.126959111,"remaining_time":0.6111752551},
{"learn":[4.896816173],"iteration":172,"passed_time":0.1273542516,"remaining_time":0.6087974919},
{"learn":[4.891123132],"iteration":173,"passed_time":0.127718903,"remaining_time":0.606297781},
{"learn":[4.887630202],"iteration":174,"passed_time":0.128098784,"remaining_time":0.6038942676},
{"learn":[4.885259712],"iteration":175,"passed_time":0.1288941753,"remaining_time":0.6034590932},
{"learn":[4.880659728],"iteration":176,"passed_time":0.129328705,"remaining_time":0.6013419447},
{"learn":[4.877299723],"iteration":177,"passed_time":0.1297585648,"remaining_time":0.5992221365},
{"learn":[4.874038772],"iteration":178,"passed_time":0.1301502456,"remaining_time":0.5969460985},
{"learn":[4.86943698],"iteration":179,"passed_time":0.1306273643,"remaining_time":0.5950802152},
{"learn":[4.861268711],"iteration":180,"passed_time":0.1311191627,"remaining_time":0.5932961008},
{"learn":[4.858673056],"iteration":181,"passed_time":0.1316373605,"remaining_time":0.5916448399},
{"learn":[4.854036207],"iteration":182,"passed_time":0.1321327388,"remaining_time":0.589904085},
{"learn":[4.85130244],"iteration":183,"passed_time":0.1326326169,"remaining_time":0.588196823},
{"learn":[4.847510084],"iteration":184,"passed_time":0.1330474571,"remaining_time":0.5861279869},
{"learn":[4.845691673],"iteration":185,"passed_time":0.1334792769,"remaining_time":0.5841512443},
{"learn":[4.842058646],"iteration":186,"passed_time":0.1338926172,"remaining_time":0.5821106833},
{"learn":[4.838623675],"iteration":187,"passed_time":0.1346409895,"remaining_time":0.5815344866},
{"learn":[4.834602161],"iteration":188,"passed_time":0.1351856766,"remaining_time":0.5800824537},
{"learn":[4.830858976],"iteration":189,"passed_time":0.1356995445,"remaining_time":0.5785085844},
{"learn":[4.827590511],"iteration":190,"passed_time":0.1361672435,"remaining_time":0.5767502615},
{"learn":[4.822246226],"iteration":191,"passed_time":0.1366275726,"remaining_time":0.5749743679},
{"learn":[4.816686395],"iteration":192,"passed_time":0.1371332306,"remaining_time":0.5734016431},
{"learn":[4.814797121],"iteration":193,"passed_time":0.1375975597,"remaining_time":0.5716682118},
{"learn":[4.811639392],"iteration":194,"passed_time":0.1380185297,"remaining_time":0.5697688022},
{"learn":[4.804813432],"iteration":195,"passed_time":0.1384395098,"remaining_time":0.5678845197},
{"learn":[4.80251613],"iteration":196,"passed_time":0.1388369304,"remaining_time":0.5659190614},
{"learn":[4.800087884],"iteration":197,"passed_time":0.13927818,"remaining_time":0.5641469714},
{"learn":[4.794773135],"iteration":198,"passed_time":0.1397145597,"remaining_time":0.5623686547},
{"learn":[4.791664833],"iteration":199,"passed_time":0.1402130879,"remaining_time":0.5608523515},
{"learn":[4.785989873],"iteration":200,"passed_time":0.1407093062,"remaining_time":0.5593369931},
{"learn":[4.782387142],"iteration":201,"passed_time":0.1411663454,"remaining_time":0.5576769485},
{"learn":[4.778623704],"iteration":202,"passed_time":0.1415884654,"remaining_time":0.5558916597},
{"learn":[4.775772178],"iteration":203,"passed_time":0.1421282326,"remaining_time":0.5545787901},
{"learn":[4.77023101],"iteration":204,"passed_time":0.1427239586,"remaining_time":0.5534904735},
{"learn":[4.764496689],"iteration":205,"passed_time":0.1432001573,"remaining_time":0.5519462374},
{"learn":[4.763138716],"iteration":206,"passed_time":0.1436905957,"remaining_time":0.5504668716},
{"learn":[4.758053283],"iteration":207,"passed_time":0.1441359652,"remaining_time":0.548825406},
{"learn":[4.755063788],"iteration":208,"passed_time":0.1445561753,"remaining_time":0.5471001658},
{"learn":[4.752465267],"iteration":209,"passed_time":0.1450112045,"remaining_time":0.5455183409},
{"learn":[4.748067377],"iteration":210,"passed_time":0.1454519141,"remaining_time":0.5438936505},
{"learn":[4.744163298],"iteration":211,"passed_time":0.1458750341,"remaining_time":0.5422147495},
{"learn":[4.736670896],"iteration":212,"passed_time":0.1462942142,"remaining_time":0.5405330826},
{"learn":[4.73349255],"iteration":213,"passed_time":0.1467023946,"remaining_time":0.5388228138},
{"learn":[4.731864595],"iteration":214,"passed_time":0.147107875,"remaining_time":0.5371147995},
{"learn":[4.728398311],"iteration":215,"passed_time":0.1475472846,"remaining_time":0.5355419961},
{"learn":[4.723865975],"iteration":216,"passed_time":0.1481155812,"remaining_time":0.5344447009},
{"learn":[4.723483365],"iteration":217,"passed_time":0.1491693863,"remaining_time":0.5350938537},
{"learn":[4.72095416],"iteration":218,"passed_time":0.1496417952,"remaining_time":0.5336540731},
{"learn":[4.716173382],"iteration":219,"passed_time":0.150112844,"remaining_time":0.5322182652},
{"learn":[4.710563974],"iteration":220,"passed_time":0.1505676333,"remaining_time":0.5307338748},
{"learn":[4.707160263],"iteration":221,"passed_time":0.1509651139,"remaining_time":0.5290579217},
{"learn":[4.70408351],"iteration":222,"passed_time":0.1513792441,"remaining_time":0.527451447},
{"learn":[4.702501831],"iteration":223,"passed_time":0.1517717148,"remaining_time":0.5257805836},
{"learn":[4.700269738],"iteration":224,"passed_time":0.1521244365,"remaining_time":0.5239841702},
{"learn":[4.695346302],"iteration":225,"passed_time":0.1524883679,"remaining_time":0.5222389237},
{"learn":[4.689769299],"iteration":226,"passed_time":0.1528571792,"remaining_time":0.5205224649},
{"learn":[4.687919514],"iteration":227,"passed_time":0.1532094309,"remaining_time":0.5187617572},
{"learn":[4.682982074],"iteration":228,"passed_time":0.1536468005,"remaining_time":0.5172999267},
{"learn":[4.679578702],"iteration":229,"passed_time":0.154136249,"remaining_time":0.5160213553},
{"learn":[4.675751423],"iteration":230,"passed_time":0.1546261174,"remaining_time":0.5147510143},
{"learn":[4.672710726],"iteration":231,"passed_time":0.1551247056,"remaining_time":0.5135162669},
{"learn":[4.6690533],"iteration":232,"passed_time":0.1555579954,"remaining_time":0.5120728862},
{"learn":[4.667595702],"iteration":233,"passed_time":0.1559665658,"remaining_time":0.5105572195},
{"learn":[4.664241291],"iteration":234,"passed_time":0.1564765937,"remaining_time":0.5093812518},
{"learn":[4.662246999],"iteration":235,"passed_time":0.1569873916,"remaining_time":0.5082134204},
{"learn":[4.658668443],"iteration":236,"passed_time":0.1574403909,"remaining_time":0.5068650561},
{"learn":[4.658017572],"iteration":237,"passed_time":0.1578949102,"remaining_time":0.5055290822},
{"learn":[4.657656705],"iteration":238,"passed_time":0.1583221801,"remaining_time":0.5041137199},
{"learn":[4.653242871],"iteration":239,"passed_time":0.1587673296,"remaining_time":0.5027632104},
{"learn":[4.6507302],"iteration":240,"passed_time":0.1591895396,"remaining_time":0.5013479692},
{"learn":[4.647671336],"iteration":241,"passed_time":0.1596019599,"remaining_time":0.499910271},
{"learn":[4.645506007],"iteration":242,"passed_time":0.1599677912,"remaining_time":0.4983358764},
{"learn":[4.641297906],"iteration":243,"passed_time":0.1603877113,"remaining_time":0.4969389744},
{"learn":[4.63798107],"iteration":244,"passed_time":0.1607617625,"remaining_time":0.4954086966},
{"learn":[4.635062318],"iteration":245,"passed_time":0.1611927423,"remaining_time":0.4940623077},
{"learn":[4.631606017],"iteration":246,"passed_time":0.1617356295,"remaining_time":0.4930644899},
{"learn":[4.630215494],"iteration":247,"passed_time":0.1622694169,"remaining_time":0.4920427479},
{"learn":[4.62729814],"iteration":248,"passed_time":0.1627084565,"remaining_time":0.4907391599},
{"learn":[4.624691756],"iteration":249,"passed_time":0.1631836153,"remaining_time":0.4895508458},
{"learn":[4.621840053],"iteration":250,"passed_time":0.1636114752,"remaining_time":0.4882270713},
{"learn":[4.619602091],"iteration":251,"passed_time":0.1639925862,"remaining_time":0.4867716446},
{"learn":[4.613584029],"iteration":252,"passed_time":0.1643997865,"remaining_time":0.4854017413},
{"learn":[4.6119388],"iteration":253,"passed_time":0.1647930673,"remaining_time":0.4839985361},
{"learn":[4.60870702],"iteration":254,"passed_time":0.1652049575,"remaining_time":0.482657621},
{"learn":[4.604771557],"iteration":255,"passed_time":0.1656111179,"remaining_time":0.4813073115},
{"learn":[4.604231277],"iteration":256,"passed_time":0.1660218582,"remaining_time":0.4799775901},
{"learn":[4.600750354],"iteration":257,"passed_time":0.1665116867,"remaining_time":0.4788824477},
{"learn":[4.596488253],"iteration":258,"passed_time":0.1669527062,"remaining_time":0.4776523371},
{"learn":[4.59470784],"iteration":259,"passed_time":0.1674201952,"remaining_time":0.4765036325},
{"learn":[4.588818005],"iteration":260,"passed_time":0.167935923,"remaining_time":0.4754967322},
{"learn":[4.585054174],"iteration":261,"passed_time":0.1684356412,"remaining_time":0.4744484855},
{"learn":[4.581471435],"iteration":262,"passed_time":0.1689365594,"remaining_time":0.4734077728},
{"learn":[4.577555199],"iteration":263,"passed_time":0.1695707544,"remaining_time":0.4727427092},
{"learn":[4.57457145],"iteration":264,"passed_time":0.1700889422,"remaining_time":0.4717561226},
{"learn":[4.573029224],"iteration":265,"passed_time":0.1704720631,"remaining_time":0.4704003546},
{"learn":[4.571326203],"iteration":266,"passed_time":0.170983751,"remaining_time":0.4694048296},
{"learn":[4.571019224],"iteration":267,"passed_time":0.1713765217,"remaining_time":0.4680881116},
{"learn":[4.565766631],"iteration":268,"passed_time":0.1718871497,"remaining_time":0.4670985368},
{"learn":[4.563383471],"iteration":269,"passed_time":0.1723941577,"remaining_time":0.4661027227},
{"learn":[4.558165805],"iteration":270,"passed_time":0.1728835361,"remaining_time":0.4650630917},
{"learn":[4.55629209],"iteration":271,"passed_time":0.1733894142,"remaining_time":0.4640716674},
{"learn":[4.549383848],"iteration":272,"passed_time":0.1738776827,"remaining_time":0.4630369058},
{"learn":[4.546227503],"iteration":273,"passed_time":0.1743365818,"remaining_time":0.4619283153},
{"learn":[4.540620977],"iteration":274,"passed_time":0.1748011608,"remaining_time":0.460839424},
{"learn":[4.532898237],"iteration":275,"passed_time":0.1752505502,"remaining_time":0.4597152115},
{"learn":[4.529757367],"iteration":276,"passed_time":0.1757427586,"remaining_time":0.4587076334},
{"learn":[4.52579294],"iteration":277,"passed_time":0.1762796259,"remaining_time":0.4578197479},
{"learn":[4.521572155],"iteration":278,"passed_time":0.1766931961,"remaining_time":0.4566157506},
{"learn":[4.518818099],"iteration":279,"passed_time":0.1771561252,"remaining_time":0.455544322},
{"learn":[4.514012334],"iteration":280,"passed_time":0.1775919949,"remaining_time":0.454407987},
{"learn":[4.508331416],"iteration":281,"passed_time":0.1779955254,"remaining_time":0.4531942809},
{"learn":[4.506038537],"iteration":282,"passed_time":0.178392466,"remaining_time":0.4519696047},
{"learn":[4.505805643],"iteration":283,"passed_time":0.1788194659,"remaining_time":0.4508265408},
{"learn":[4.501550352],"iteration":284,"passed_time":0.1792472658,"remaining_time":0.449690509},
{"learn":[4.494692643],"iteration":285,"passed_time":0.1796661559,"remaining_time":0.4485371865},
{"learn":[4.489330245],"iteration":286,"passed_time":0.1801193752,"remaining_time":0.4474742666},
{"learn":[4.484826955],"iteration":287,"passed_time":0.1805754544,"remaining_time":0.4464226512},
{"learn":[4.478285428],"iteration":288,"passed_time":0.1810418834,"remaining_time":0.4454006198},
{"learn":[4.475311671],"iteration":289,"passed_time":0.1814950927,"remaining_time":0.4443500546},
{"learn":[4.471581298],"iteration":290,"passed_time":0.1819338823,"remaining_time":0.4432684625},
{"learn":[4.469164956],"iteration":291,"passed_time":0.1823639522,"remaining_time":0.4421701307},
{"learn":[4.462068024],"iteration":292,"passed_time":0.1828240113,"remaining_time":0.4411487236},
{"learn":[4.458540976],"iteration":293,"passed_time":0.1832741107,"remaining_time":0.4401072182},
{"learn":[4.455757458],"iteration":294,"passed_time":0.183684661,"remaining_time":0.4389752068},
{"learn":[4.453027414],"iteration":295,"passed_time":0.1840778517,"remaining_time":0.4378067824},
{"learn":[4.450659338],"iteration":296,"passed_time":0.1844918119,"remaining_time":0.43669274},
{"learn":[4.444696901],"iteration":297,"passed_time":0.1848933324,"remaining_time":0.4355540919},
{"learn":[4.442052813],"iteration":298,"passed_time":0.1853390619,"remaining_time":0.4345240214},
{"learn":[4.440036756],"iteration":299,"passed_time":0.1858108508,"remaining_time":0.4335586518},
{"learn":[4.435017051],"iteration":300,"passed_time":0.1863236787,"remaining_time":0.432691865},
{"learn":[4.429962125],"iteration":301,"passed_time":0.1867942875,"remaining_time":0.4317298434},
{"learn":[4.427666256],"iteration":302,"passed_time":0.1872733962,"remaining_time":0.4307906177},
{"learn":[4.425030004],"iteration":303,"passed_time":0.1876671469,"remaining_time":0.4296589943},
{"learn":[4.422588771],"iteration":304,"passed_time":0.1880825871,"remaining_time":0.4285816329},
{"learn":[4.418936667],"iteration":305,"passed_time":0.1885256066,"remaining_time":0.4275711471},
{"learn":[4.416887976],"iteration":306,"passed_time":0.1889403868,"remaining_time":0.4265006126},
{"learn":[4.413773354],"iteration":307,"passed_time":0.1893316076,"remaining_time":0.4253814041},
{"learn":[4.411129391],"iteration":308,"passed_time":0.1897074087,"remaining_time":0.4242324253},
{"learn":[4.40850819],"iteration":309,"passed_time":0.1901098692,"remaining_time":0.4231477734},
{"learn":[4.404880292],"iteration":310,"passed_time":0.1905218095,"remaining_time":0.4220885104},
{"learn":[4.404593827],"iteration":311,"passed_time":0.1908959606,"remaining_time":0.4209500671},
{"learn":[4.402139942],"iteration":312,"passed_time":0.1912734617,"remaining_time":0.4198238601},
{"learn":[4.400284725],"iteration":313,"passed_time":0.1916544827,"remaining_time":0.4187101119},
{"learn":[4.395805521],"iteration":314,"passed_time":0.1920875125,"remaining_time":0.4177141145},
{"learn":[4.392838833],"iteration":315,"passed_time":0.192488593,"remaining_time":0.4166525241},
{"learn":[4.389213061],"iteration":316,"passed_time":0.192911053,"remaining_time":0.4156411648},
{"learn":[4.3861981],"iteration":317,"passed_time":0.193376652,"remaining_time":0.4147260273},
{"learn":[4.385054234],"iteration":318,"passed_time":0.1938046719,"remaining_time":0.4137334846},
{"learn":[4.379364607],"iteration":319,"passed_time":0.1941859429,"remaining_time":0.4126451287},
{"learn":[4.378387619],"iteration":320,"passed_time":0.1945666539,"remaining_time":0.4115599938},
{"learn":[4.375816727],"iteration":321,"passed_time":0.1949760843,"remaining_time":0.4105397054},
{"learn":[4.374600202],"iteration":322,"passed_time":0.1954147939,"remaining_time":0.409584568},
{"learn":[4.37098897],"iteration":323,"passed_time":0.1958154044,"remaining_time":0.4085531278},
{"learn":[4.367418484],"iteration":324,"passed_time":0.196216235,"remaining_time":0.4075260265},
{"learn":[4.363584638],"iteration":325,"passed_time":0.1966195554,"remaining_time":0.4065079152},
{"learn":[4.360770706],"iteration":326,"passed_time":0.1970386155,"remaining_time":0.405525958},
{"learn":[4.358675808],"iteration":327,"passed_time":0.1974586856,"remaining_time":0.4045495022},
{"learn":[4.354228195],"iteration":328,"passed_time":0.1978967553,"remaining_time":0.4036131392},
{"learn":[4.353773425],"iteration":329,"passed_time":0.1983041457,"remaining_time":0.4026175078},
{"learn":[4.351648009],"iteration":330,"passed_time":0.198754995,"remaining_time":0.4017132678},
{"learn":[4.348209927],"iteration":331,"passed_time":0.1997252921,"remaining_time":0.401856913},
{"learn":[4.345852733],"iteration":332,"passed_time":0.2007390281,"remaining_time":0.4020808762},
{"learn":[4.34237339],"iteration":333,"passed_time":0.2017154951,"remaining_time":0.4022231129},
{"learn":[4.340814362],"iteration":334,"passed_time":0.2025884144,"remaining_time":0.4021531212},
{"learn":[4.339707068],"iteration":335,"passed_time":0.2034018452,"remaining_time":0.4019607894},
{"learn":[4.335430786],"iteration":336,"passed_time":0.2041586474,"remaining_time":0.4016533626},
{"learn":[4.33521887],"iteration":337,"passed_time":0.2049207594,"remaining_time":0.4013536766},
{"learn":[4.328507238],"iteration":338,"passed_time":0.2057369401,"remaining_time":0.4011566885},
{"learn":[4.326140732],"iteration":339,"passed_time":0.2064256138,"remaining_time":0.4007085444},
{"learn":[4.323785636],"iteration":340,"passed_time":0.2073630417,"remaining_time":0.4007397198},
{"learn":[4.320632534],"iteration":341,"passed_time":0.2084325864,"remaining_time":0.4010194206},
{"learn":[4.31973724],"iteration":342,"passed_time":0.209296446,"remaining_time":0.4008972741},
{"learn":[4.318000924],"iteration":343,"passed_time":0.2101113267,"remaining_time":0.4006774138},
{"learn":[4.312713628],"iteration":344,"passed_time":0.2111497522,"remaining_time":0.4008785151},
{"learn":[4.308220789],"iteration":345,"passed_time":0.2128238527,"remaining_time":0.4022739874},
{"learn":[4.305890947],"iteration":346,"passed_time":0.2138647481,"remaining_time":0.4024601743},
{"learn":[4.305137856],"iteration":347,"passed_time":0.2146489596,"remaining_time":0.4021583955},
{"learn":[4.304787172],"iteration":348,"passed_time":0.2153561928,"remaining_time":0.4017102623},
{"learn":[4.30350134],"iteration":349,"passed_time":0.2160917255,"remaining_time":0.4013132044},
{"learn":[4.30293809],"iteration":350,"passed_time":0.2168664472,"remaining_time":0.4009866787},
{"learn":[4.299548459],"iteration":351,"passed_time":0.217805985,"remaining_time":0.4009610178},
{"learn":[4.294768408],"iteration":352,"passed_time":0.2186690846,"remaining_time":0.4007900786},
{"learn":[4.294581479],"iteration":353,"passed_time":0.2195048848,"remaining_time":0.4005654113},
{"learn":[4.292551604],"iteration":354,"passed_time":0.2204161033,"remaining_time":0.4004743286},
{"learn":[4.288628894],"iteration":355,"passed_time":0.2211955249,"remaining_time":0.4001402192},
{"learn":[4.287802767],"iteration":356,"passed_time":0.2219886762,"remaining_time":0.3998283439},
{"learn":[4.284566905],"iteration":357,"passed_time":0.2229216241,"remaining_time":0.3997644768},
{"learn":[4.27890232],"iteration":358,"passed_time":0.2238668618,"remaining_time":0.3997177115},
{"learn":[4.276938023],"iteration":359,"passed_time":0.2257156881,"remaining_time":0.4012723345},
{"learn":[4.273425094],"iteration":360,"passed_time":0.2269372293,"remaining_time":0.4016977549},
{"learn":[4.269726505],"iteration":361,"passed_time":0.2278308182,"remaining_time":0.4015360829},
{"learn":[4.265565857],"iteration":362,"passed_time":0.2287444566,"remaining_time":0.4014055616},
{"learn":[4.262117173],"iteration":363,"passed_time":0.2292301751,"remaining_time":0.4005230532},
{"learn":[4.259185148],"iteration":364,"passed_time":0.2296785345,"remaining_time":0.3995777244},
{"learn":[4.257668507],"iteration":365,"passed_time":0.2300973946,"remaining_time":0.3985840115},
{"learn":[4.253432436],"iteration":366,"passed_time":0.2305533839,"remaining_time":0.3976574713},
{"learn":[4.250216667],"iteration":367,"passed_time":0.2309968634,"remaining_time":0.3967120045},
{"learn":[4.24514828],"iteration":368,"passed_time":0.2314063237,"remaining_time":0.3957110847},
{"learn":[4.244015772],"iteration":369,"passed_time":0.2317862047,"remaining_time":0.3946629973},
{"learn":[4.240329192],"iteration":370,"passed_time":0.232199795,"remaining_time":0.3936756632},
{"learn":[4.236718014],"iteration":371,"passed_time":0.2326054454,"remaining_time":0.3926780099},
{"learn":[4.233495944],"iteration":372,"passed_time":0.2329841364,"remaining_time":0.3916382133},
{"learn":[4.230357491],"iteration":373,"passed_time":0.2333686474,"remaining_time":0.3906116932},
{"learn":[4.227381215],"iteration":374,"passed_time":0.2337186291,"remaining_time":0.3895310485},
{"learn":[4.226169067],"iteration":375,"passed_time":0.2340998201,"remaining_time":0.3885060844},
{"learn":[4.225963861],"iteration":376,"passed_time":0.2344584516,"remaining_time":0.3874472556},
{"learn":[4.224346548],"iteration":377,"passed_time":0.234822503,"remaining_time":0.3864010499},
{"learn":[4.222595381],"iteration":378,"passed_time":0.2351939842,"remaining_time":0.385370618},
{"learn":[4.219700938],"iteration":379,"passed_time":0.2355955248,"remaining_time":0.3843926983},
{"learn":[4.216356207],"iteration":380,"passed_time":0.2360540439,"remaining_time":0.3835103758},
{"learn":[4.214326494],"iteration":381,"passed_time":0.2364796639,"remaining_time":0.3825770478},
{"learn":[4.212901398],"iteration":382,"passed_time":0.2368947841,"remaining_time":0.3816294563},
{"learn":[4.211331091],"iteration":383,"passed_time":0.2372712152,"remaining_time":0.3806225743},
{"learn":[4.208624791],"iteration":384,"passed_time":0.2376655259,"remaining_time":0.3796475283},
{"learn":[4.204659106],"iteration":385,"passed_time":0.2380719663,"remaining_time":0.3786947857},
{"learn":[4.202968852],"iteration":386,"passed_time":0.2384314478,"remaining_time":0.3776704844},
{"learn":[4.197261935],"iteration":387,"passed_time":0.2388764472,"remaining_time":0.3767844993},
{"learn":[4.196934403],"iteration":388,"passed_time":0.2393190068,"remaining_time":0.375896949},
{"learn":[4.192479929],"iteration":389,"passed_time":0.2398097752,"remaining_time":0.3750870843},
{"learn":[4.190243116],"iteration":390,"passed_time":0.2402312252,"remaining_time":0.3741708854},
{"learn":[4.185852431],"iteration":391,"passed_time":0.2406841345,"remaining_time":0.3733060046},
{"learn":[4.180967944],"iteration":392,"passed_time":0.2411080345,"remaining_time":0.3723984147},
{"learn":[4.178283162],"iteration":393,"passed_time":0.241469846,"remaining_time":0.3713977834},
{"learn":[4.176341157],"iteration":394,"passed_time":0.2418715665,"remaining_time":0.3704615132},
{"learn":[4.176041504],"iteration":395,"passed_time":0.2423440953,"remaining_time":0.3696359434},
{"learn":[4.175564513],"iteration":396,"passed_time":0.2427960447,"remaining_time":0.368780894},
{"learn":[4.170830274],"iteration":397,"passed_time":0.2432223846,"remaining_time":0.3678891345},
{"learn":[4.167804808],"iteration":398,"passed_time":0.2436547344,"remaining_time":0.3670087603},
{"learn":[4.165860548],"iteration":399,"passed_time":0.2440463951,"remaining_time":0.3660695927},
{"learn":[4.160950571],"iteration":400,"passed_time":0.2444443157,"remaining_time":0.3651425065},
{"learn":[4.158544115],"iteration":401,"passed_time":0.2448095871,"remaining_time":0.3641694853},
{"learn":[4.154448767],"iteration":402,"passed_time":0.2452035478,"remaining_time":0.3632419802},
{"learn":[4.15197457],"iteration":403,"passed_time":0.2455975985,"remaining_time":0.3623172492},
{"learn":[4.149562679],"iteration":404,"passed_time":0.2460584076,"remaining_time":0.3614932161},
{"learn":[4.149327961],"iteration":405,"passed_time":0.2464155792,"remaining_time":0.3605193449},
{"learn":[4.147444889],"iteration":406,"passed_time":0.2467885603,"remaining_time":0.3595715388},
{"learn":[4.147254809],"iteration":407,"passed_time":0.2471965807,"remaining_time":0.3586773916},
{"learn":[4.144589165],"iteration":408,"passed_time":0.2476100409,"remaining_time":0.3577934821},
{"learn":[4.141691034],"iteration":409,"passed_time":0.2480380008,"remaining_time":0.3569327329},
{"learn":[4.138893468],"iteration":410,"passed_time":0.2484904901,"remaining_time":0.3561092426},
{"learn":[4.136964597],"iteration":411,"passed_time":0.2489087703,"remaining_time":0.3552387304},
{"learn":[4.133773523],"iteration":412,"passed_time":0.2493547797,"remaining_time":0.3544098201},
{"learn":[4.131363444],"iteration":413,"passed_time":0.2497566002,"remaining_time":0.3535202119},
{"learn":[4.130228592],"iteration":414,"passed_time":0.2503118071,"remaining_time":0.3528491739},
{"learn":[4.12884186],"iteration":415,"passed_time":0.2513923416,"remaining_time":0.3529161719},
{"learn":[4.12413494],"iteration":416,"passed_time":0.2518855399,"remaining_time":0.3521565223},
{"learn":[4.119422508],"iteration":417,"passed_time":0.252393048,"remaining_time":0.3514180716},
{"learn":[4.117038244],"iteration":418,"passed_time":0.2528630569,"remaining_time":0.3506287256},
{"learn":[4.116067631],"iteration":419,"passed_time":0.2533503253,"remaining_time":0.349864735},
{"learn":[4.110343455],"iteration":420,"passed_time":0.2538086845,"remaining_time":0.3490623001},
{"learn":[4.105604544],"iteration":421,"passed_time":0.2542410343,"remaining_time":0.3482258716},
{"learn":[4.103390131],"iteration":422,"passed_time":0.2547409025,"remaining_time":0.3474834533},
{"learn":[4.096724402],"iteration":423,"passed_time":0.255186302,"remaining_time":0.3466681838},
{"learn":[4.093431279],"iteration":424,"passed_time":0.2556216717,"remaining_time":0.3458410852},
{"learn":[4.091412744],"iteration":425,"passed_time":0.2561178,"remaining_time":0.3450976929},
{"learn":[4.091192901],"iteration":426,"passed_time":0.2566065384,"remaining_time":0.3443455422},
{"learn":[4.088994581],"iteration":427,"passed_time":0.2570669976,"remaining_time":0.3435568285},
{"learn":[4.087845355],"iteration":428,"passed_time":0.2575645458,"remaining_time":0.3428190108},
{"learn":[4.083650279],"iteration":429,"passed_time":0.2580359847,"remaining_time":0.3420477006},
{"learn":[4.079840652],"iteration":430,"passed_time":0.2585683421,"remaining_time":0.3413582057},
{"learn":[4.075707828],"iteration":431,"passed_time":0.2590674203,"remaining_time":0.3406256822},
{"learn":[4.071345409],"iteration":432,"passed_time":0.25950402,"remaining_time":0.3398124234},
{"learn":[4.067460475],"iteration":433,"passed_time":0.2599237701,"remaining_time":0.3389789259},
{"learn":[4.064914749],"iteration":434,"passed_time":0.2603869291,"remaining_time":0.3382037125},
{"learn":[4.063823175],"iteration":435,"passed_time":0.2608316186,"remaining_time":0.3374060388},
{"learn":[4.058898471],"iteration":436,"passed_time":0.2613338168,"remaining_time":0.3366840706},
{"learn":[4.054120355],"iteration":437,"passed_time":0.2617637566,"remaining_time":0.3358703909},
{"learn":[4.052715901],"iteration":438,"passed_time":0.2621512075,"remaining_time":0.3350041626},
{"learn":[4.052114167],"iteration":439,"passed_time":0.2625730275,"remaining_time":0.3341838532},
{"learn":[4.051377267],"iteration":440,"passed_time":0.2630353466,"remaining_time":0.3334166865},
{"learn":[4.049275336],"iteration":441,"passed_time":0.2636133129,"remaining_time":0.3327968973},
{"learn":[4.047099198],"iteration":442,"passed_time":0.2641923592,"remaining_time":0.3321786548},
{"learn":[4.044348685],"iteration":443,"passed_time":0.2648017148,"remaining_time":0.3315985438},
{"learn":[4.042822379],"iteration":444,"passed_time":0.2653376422,"remaining_time":0.3309267223},
{"learn":[4.041258611],"iteration":445,"passed_time":0.2658816893,"remaining_time":0.3302655962},
{"learn":[4.040044254],"iteration":446,"passed_time":0.2664237265,"remaining_time":0.3296025073},
{"learn":[4.036860137],"iteration":447,"passed_time":0.2670215124,"remaining_time":0.3290086492},
{"learn":[4.036372284],"iteration":448,"passed_time":0.2674926313,"remaining_time":0.3282593315},
{"learn":[4.03368231],"iteration":449,"passed_time":0.2679891095,"remaining_time":0.327542245},
{"learn":[4.032439519],"iteration":450,"passed_time":0.2684632283,"remaining_time":0.3267989188},
{"learn":[4.032008634],"iteration":451,"passed_time":0.2688982881,"remaining_time":0.3260094289},
{"learn":[4.030034932],"iteration":452,"passed_time":0.2693440875,"remaining_time":0.3252344722},
{"learn":[4.028173412],"iteration":453,"passed_time":0.2697719774,"remaining_time":0.3244394266},
{"learn":[4.023806097],"iteration":454,"passed_time":0.270298695,"remaining_time":0.3237643709},
{"learn":[4.020239186],"iteration":455,"passed_time":0.271019778,"remaining_time":0.3233218404},
{"learn":[4.017384838],"iteration":456,"passed_time":0.2716141839,"remaining_time":0.3227275752},
{"learn":[4.016468229],"iteration":457,"passed_time":0.2721098522,"remaining_time":0.3220164627},
{"learn":[4.014530169],"iteration":458,"passed_time":0.2726176902,"remaining_time":0.3213206327},
{"learn":[4.012884822],"iteration":459,"passed_time":0.2730799693,"remaining_time":0.3205721379},
{"learn":[4.008924707],"iteration":460,"passed_time":0.2734811498,"remaining_time":0.3197534485},
{"learn":[4.008286778],"iteration":461,"passed_time":0.273855551,"remaining_time":0.3189053819},
{"learn":[4.006444202],"iteration":462,"passed_time":0.2743754387,"remaining_time":0.3182281006},
{"learn":[4.003284363],"iteration":463,"passed_time":0.2752277386,"remaining_time":0.3179354911},
{"learn":[3.999811484],"iteration":464,"passed_time":0.2774040271,"remaining_time":0.3191637732},
{"learn":[3.997483319],"iteration":465,"passed_time":0.2795204172,"remaining_time":0.3203088042},
{"learn":[3.99708333],"iteration":466,"passed_time":0.2802378202,"remaining_time":0.3198431652},
{"learn":[3.995860263],"iteration":467,"passed_time":0.2807045592,"remaining_time":0.3190915074},
{"learn":[3.994131111],"iteration":468,"passed_time":0.2811273492,"remaining_time":0.3182913058},
{"learn":[3.993125499],"iteration":469,"passed_time":0.2815544891,"remaining_time":0.3174976154},
{"learn":[3.992954084],"iteration":470,"passed_time":0.2819738392,"remaining_time":0.3166967324},
{"learn":[3.990635743],"iteration":471,"passed_time":0.2823856495,"remaining_time":0.3158890316},
{"learn":[3.986678254],"iteration":472,"passed_time":0.2828186692,"remaining_time":0.3151066357},
{"learn":[3.986393291],"iteration":473,"passed_time":0.2832371194,"remaining_time":0.314309546},
{"learn":[3.986152671],"iteration":474,"passed_time":0.2836369399,"remaining_time":0.3134934599},
{"learn":[3.985596662],"iteration":475,"passed_time":0.2840463902,"remaining_time":0.3126897237},
{"learn":[3.983853457],"iteration":476,"passed_time":0.2845043594,"remaining_time":0.3119408385},
{"learn":[3.983263928],"iteration":477,"passed_time":0.2850158573,"remaining_time":0.3112516266},
{"learn":[3.980067202],"iteration":478,"passed_time":0.2854705766,"remaining_time":0.3105013996},
{"learn":[3.978115407],"iteration":479,"passed_time":0.2859562451,"remaining_time":0.3097859322},
{"learn":[3.972661644],"iteration":480,"passed_time":0.2864723529,"remaining_time":0.3091042644},
{"learn":[3.969938254],"iteration":481,"passed_time":0.2869917107,"remaining_time":0.3084267762},
{"learn":[3.968211434],"iteration":482,"passed_time":0.2874537498,"remaining_time":0.3076885893},
{"learn":[3.966113368],"iteration":483,"passed_time":0.2878784597,"remaining_time":0.3069117463},
{"learn":[3.962246044],"iteration":484,"passed_time":0.2883209393,"remaining_time":0.3061552242},
{"learn":[3.961319703],"iteration":485,"passed_time":0.2887771185,"remaining_time":0.3054144833},
{"learn":[3.96078191],"iteration":486,"passed_time":0.2892844265,"remaining_time":0.3047287696},
{"learn":[3.958913633],"iteration":487,"passed_time":0.2897385858,"remaining_time":0.3039880244},
{"learn":[3.957428286],"iteration":488,"passed_time":0.2901766154,"remaining_time":0.3032315961},
{"learn":[3.952641965],"iteration":489,"passed_time":0.2906238649,"remaining_time":0.3024860634},
{"learn":[3.951486786],"iteration":490,"passed_time":0.2910984137,"remaining_time":0.3017700459},
{"learn":[3.94938344],"iteration":491,"passed_time":0.2915650026,"remaining_time":0.3010467913},
{"learn":[3.947297924],"iteration":492,"passed_time":0.2920884503,"remaining_time":0.3003830513},
{"learn":[3.946284886],"iteration":493,"passed_time":0.2926002982,"remaining_time":0.2997079977},
{"learn":[3.943288204],"iteration":494,"passed_time":0.293074747,"remaining_time":0.2989954489},
{"learn":[3.943076488],"iteration":495,"passed_time":0.2935137766,"remaining_time":0.2982478698},
{"learn":[3.942347078],"iteration":496,"passed_time":0.2939434965,"remaining_time":0.2974921101},
{"learn":[3.940251541],"iteration":497,"passed_time":0.2943568467,"remaining_time":0.2967211587},
{"learn":[3.939011019],"iteration":498,"passed_time":0.2947871365,"remaining_time":0.2959686481},
{"learn":[3.938760512],"iteration":499,"passed_time":0.2951854971,"remaining_time":0.2951854971},
{"learn":[3.934522727],"iteration":500,"passed_time":0.295656106,"remaining_time":0.2944758421},
{"learn":[3.930091193],"iteration":501,"passed_time":0.2962286525,"remaining_time":0.2938682648},
{"learn":[3.927671752],"iteration":502,"passed_time":0.2967634098,"remaining_time":0.2932234885},
{"learn":[3.927280041],"iteration":503,"passed_time":0.2972669679,"remaining_time":0.2925484446},
{"learn":[3.925987561],"iteration":504,"passed_time":0.2978120351,"remaining_time":0.291914767},
{"learn":[3.921645957],"iteration":505,"passed_time":0.2983583422,"remaining_time":0.2912826503},
{"learn":[3.920333743],"iteration":506,"passed_time":0.2988415508,"remaining_time":0.2905895158},
{"learn":[3.918659461],"iteration":507,"passed_time":0.2993103897,"remaining_time":0.2898832908},
{"learn":[3.916124385],"iteration":508,"passed_time":0.2996994205,"remaining_time":0.2891010127},
{"learn":[3.913849268],"iteration":509,"passed_time":0.300056592,"remaining_time":0.2882896669},
{"learn":[3.912826119],"iteration":510,"passed_time":0.3004284733,"remaining_time":0.287494175},
{"learn":[3.910034145],"iteration":511,"passed_time":0.3007838649,"remaining_time":0.2866846212},
{"learn":[3.90792379],"iteration":512,"passed_time":0.3011895653,"remaining_time":0.2859245971},
{"learn":[3.907823851],"iteration":513,"passed_time":0.3015241774,"remaining_time":0.2850987358},
{"learn":[3.904527401],"iteration":514,"passed_time":0.301878659,"remaining_time":0.2842934944},
{"learn":[3.903378283],"iteration":515,"passed_time":0.302216131,"remaining_time":0.2834740454},
{"learn":[3.902170135],"iteration":516,"passed_time":0.3026183015,"remaining_time":0.2827169045},
{"learn":[3.899435429],"iteration":517,"passed_time":0.3031382593,"remaining_time":0.2820707354},
{"learn":[3.897497505],"iteration":518,"passed_time":0.3035119804,"remaining_time":0.2812895233},
{"learn":[3.896426119],"iteration":519,"passed_time":0.3038740919,"remaining_time":0.2804991617},
{"learn":[3.896044669],"iteration":520,"passed_time":0.3042165138,"remaining_time":0.2796923418},
{"learn":[3.892795942],"iteration":521,"passed_time":0.3045616256,"remaining_time":0.2788897645},
{"learn":[3.892413888],"iteration":522,"passed_time":0.3049168872,"remaining_time":0.2780981935},
{"learn":[3.891738985],"iteration":523,"passed_time":0.3052574792,"remaining_time":0.277294962},
{"learn":[3.88822057],"iteration":524,"passed_time":0.3056184707,"remaining_time":0.2765119497},
{"learn":[3.883837053],"iteration":525,"passed_time":0.3059897619,"remaining_time":0.2757398235},
{"learn":[3.881769742],"iteration":526,"passed_time":0.3063829626,"remaining_time":0.2749888829},
{"learn":[3.880356898],"iteration":527,"passed_time":0.3069389395,"remaining_time":0.2743848095},
{"learn":[3.879250273],"iteration":528,"passed_time":0.3074358477,"remaining_time":0.2737283257},
{"learn":[3.877174493],"iteration":529,"passed_time":0.3079186963,"remaining_time":0.273059976},
{"learn":[3.875854201],"iteration":530,"passed_time":0.3084027649,"remaining_time":0.2723934025},
{"learn":[3.873189396],"iteration":531,"passed_time":0.3087871258,"remaining_time":0.2716398024},
{"learn":[3.871583368],"iteration":532,"passed_time":0.3093233032,"remaining_time":0.2710206052},
{"learn":[3.869622679],"iteration":533,"passed_time":0.3097787624,"remaining_time":0.2703312795},
{"learn":[3.866860164],"iteration":534,"passed_time":0.3101717631,"remaining_time":0.2695885418},
{"learn":[3.864498444],"iteration":535,"passed_time":0.3105385944,"remaining_time":0.2688244549},
{"learn":[3.861416322],"iteration":536,"passed_time":0.3109100357,"remaining_time":0.2680658222},
{"learn":[3.860265769],"iteration":537,"passed_time":0.3112801569,"remaining_time":0.2673074954},
{"learn":[3.859328725],"iteration":538,"passed_time":0.3116438883,"remaining_time":0.2665451438},
{"learn":[3.858521278],"iteration":539,"passed_time":0.3120031798,"remaining_time":0.2657804865},
{"learn":[3.85599111],"iteration":540,"passed_time":0.3123689212,"remaining_time":0.2650228001},
{"learn":[3.852379816],"iteration":541,"passed_time":0.3127560621,"remaining_time":0.2642846428},
{"learn":[3.851327537],"iteration":542,"passed_time":0.3131222834,"remaining_time":0.2635301722},
{"learn":[3.847854898],"iteration":543,"passed_time":0.3137486886,"remaining_time":0.2629952243},
{"learn":[3.847083414],"iteration":544,"passed_time":0.3141343995,"remaining_time":0.2622589941},
{"learn":[3.845397429],"iteration":545,"passed_time":0.3145227903,"remaining_time":0.2615262762},
{"learn":[3.841933528],"iteration":546,"passed_time":0.3149210509,"remaining_time":0.260802991},
{"learn":[3.840996474],"iteration":547,"passed_time":0.3153171916,"remaining_time":0.2600791434},
{"learn":[3.838355966],"iteration":548,"passed_time":0.3157097523,"remaining_time":0.2593535488},
{"learn":[3.83342799],"iteration":549,"passed_time":0.3161237125,"remaining_time":0.2586466739},
{"learn":[3.828161535],"iteration":550,"passed_time":0.3165077734,"remaining_time":0.2579164978},
{"learn":[3.823502399],"iteration":551,"passed_time":0.3168907144,"remaining_time":0.2571866668},
{"learn":[3.820068862],"iteration":552,"passed_time":0.3173386238,"remaining_time":0.2565106055},
{"learn":[3.817951642],"iteration":553,"passed_time":0.3181857138,"remaining_time":0.2561567299},
{"learn":[3.815785958],"iteration":554,"passed_time":0.318558305,"remaining_time":0.2554206229},
{"learn":[3.81503012],"iteration":555,"passed_time":0.3189004169,"remaining_time":0.254661484},
{"learn":[3.813529315],"iteration":556,"passed_time":0.3192857578,"remaining_time":0.2539382239},
{"learn":[3.808881326],"iteration":557,"passed_time":0.3196892383,"remaining_time":0.2532305436},
{"learn":[3.808740434],"iteration":558,"passed_time":0.3200941587,"remaining_time":0.2525250876},
{"learn":[3.80714352],"iteration":559,"passed_time":0.3205676375,"remaining_time":0.2518745723},
{"learn":[3.80573346],"iteration":560,"passed_time":0.3230186696,"remaining_time":0.2527721853},
{"learn":[3.803370052],"iteration":561,"passed_time":0.3235586969,"remaining_time":0.2521685218},
{"learn":[3.803215211],"iteration":562,"passed_time":0.3240754247,"remaining_time":0.2515469993},
{"learn":[3.801309667],"iteration":563,"passed_time":0.3245897625,"remaining_time":0.2509240008},
{"learn":[3.800003847],"iteration":564,"passed_time":0.3249838332,"remaining_time":0.2502087919},
{"learn":[3.798026138],"iteration":565,"passed_time":0.3253905636,"remaining_time":0.2495044251},
{"learn":[3.794745847],"iteration":566,"passed_time":0.3257948041,"remaining_time":0.2487992066},
{"learn":[3.794312041],"iteration":567,"passed_time":0.3261752151,"remaining_time":0.2480769241},
{"learn":[3.792205926],"iteration":568,"passed_time":0.326561026,"remaining_time":0.2473599335},
{"learn":[3.788991061],"iteration":569,"passed_time":0.3269321272,"remaining_time":0.2466330082},
{"learn":[3.787391572],"iteration":570,"passed_time":0.3273275579,"remaining_time":0.2459256083},
{"learn":[3.7826445],"iteration":571,"passed_time":0.3277097488,"remaining_time":0.2452093925},
{"learn":[3.781700331],"iteration":572,"passed_time":0.3281419686,"remaining_time":0.2445316241},
{"learn":[3.780045374],"iteration":573,"passed_time":0.3285186397,"remaining_time":0.2438134852},
{"learn":[3.775462644],"iteration":574,"passed_time":0.3289149604,"remaining_time":0.2431110577},
{"learn":[3.773711943],"iteration":575,"passed_time":0.3292901215,"remaining_time":0.2423941172},
{"learn":[3.772415806],"iteration":576,"passed_time":0.3297918996,"remaining_time":0.2417711847},
{"learn":[3.770170875],"iteration":577,"passed_time":0.3302203195,"remaining_time":0.2410951122},
{"learn":[3.765166479],"iteration":578,"passed_time":0.3306826286,"remaining_time":0.2404445365},
{"learn":[3.763976102],"iteration":579,"passed_time":0.3310802892,"remaining_time":0.2397477956},
{"learn":[3.760761708],"iteration":580,"passed_time":0.33147025,"remaining_time":0.2390465314},
{"learn":[3.758155662],"iteration":581,"passed_time":0.3318630507,"remaining_time":0.2383483766},
{"learn":[3.756844548],"iteration":582,"passed_time":0.3322786009,"remaining_time":0.2376675413},
{"learn":[3.753098923],"iteration":583,"passed_time":0.3326897912,"remaining_time":0.2369845088},
{"learn":[3.751618946],"iteration":584,"passed_time":0.3330756321,"remaining_time":0.2362844228},
{"learn":[3.751398464],"iteration":585,"passed_time":0.3334722827,"remaining_time":0.2355930461},
{"learn":[3.749920103],"iteration":586,"passed_time":0.3338583936,"remaining_time":0.2348952582},
{"learn":[3.748237465],"iteration":587,"passed_time":0.3342855535,"remaining_time":0.2342272926},
{"learn":[3.746021536],"iteration":588,"passed_time":0.3347262831,"remaining_time":0.2335696135},
{"learn":[3.74417648],"iteration":589,"passed_time":0.3351150539,"remaining_time":0.2328765629},
{"learn":[3.738788389],"iteration":590,"passed_time":0.3355606934,"remaining_time":0.2322238978},
{"learn":[3.736021611],"iteration":591,"passed_time":0.3360336722,"remaining_time":0.2315907741},
{"learn":[3.734546151],"iteration":592,"passed_time":0.3369879197,"remaining_time":0.2312885047},
{"learn":[3.733527479],"iteration":593,"passed_time":0.3374844779,"remaining_time":0.2306712088},
{"learn":[3.733026392],"iteration":594,"passed_time":0.3379608967,"remaining_time":0.2300406103},
{"learn":[3.730314752],"iteration":595,"passed_time":0.3384105361,"remaining_time":0.2293923768},
{"learn":[3.727342596],"iteration":596,"passed_time":0.3388186564,"remaining_time":0.2287167815},
{"learn":[3.725459604],"iteration":597,"passed_time":0.3391836278,"remaining_time":0.2280130742},
{"learn":[3.723158842],"iteration":598,"passed_time":0.3395471692,"remaining_time":0.2273095407},
{"learn":[3.722362756],"iteration":599,"passed_time":0.3399134005,"remaining_time":0.2266089337},
{"learn":[3.721443615],"iteration":600,"passed_time":0.3403105412,"remaining_time":0.2259299599},
{"learn":[3.720743486],"iteration":601,"passed_time":0.3406810924,"remaining_time":0.2252343435},
{"learn":[3.720215334],"iteration":602,"passed_time":0.3410969326,"remaining_time":0.2245696223},
{"learn":[3.719436563],"iteration":603,"passed_time":0.3414749437,"remaining_time":0.2238809233},
{"learn":[3.715046574],"iteration":604,"passed_time":0.3418612645,"remaining_time":0.2231986768},
{"learn":[3.71443396],"iteration":605,"passed_time":0.3422907144,"remaining_time":0.222545448},
{"learn":[3.712938941],"iteration":606,"passed_time":0.3426746853,"remaining_time":0.2218635113},
{"learn":[3.712814764],"iteration":607,"passed_time":0.3430578163,"remaining_time":0.2211820131},
{"learn":[3.71235348],"iteration":608,"passed_time":0.3434389173,"remaining_time":0.2205001915},
{"learn":[3.711223749],"iteration":609,"passed_time":0.3438434377,"remaining_time":0.219834329},
{"learn":[3.710755648],"iteration":610,"passed_time":0.3442391784,"remaining_time":0.2191637322},
{"learn":[3.708668039],"iteration":611,"passed_time":0.3446477687,"remaining_time":0.2185021802},
{"learn":[3.705623591],"iteration":612,"passed_time":0.3450637789,"remaining_time":0.2178461377},
{"learn":[3.704045802],"iteration":613,"passed_time":0.3455192681,"remaining_time":0.2172156962},
{"learn":[3.699915209],"iteration":614,"passed_time":0.3459389682,"remaining_time":0.2165634191},
{"learn":[3.696182221],"iteration":615,"passed_time":0.3463468986,"remaining_time":0.2159045602},
{"learn":[3.694263278],"iteration":616,"passed_time":0.3467382493,"remaining_time":0.2152362228},
{"learn":[3.693810229],"iteration":617,"passed_time":0.3471246702,"remaining_time":0.2145657347},
{"learn":[3.690900932],"iteration":618,"passed_time":0.3475264907,"remaining_time":0.2139056429},
{"learn":[3.688020895],"iteration":619,"passed_time":0.3479721202,"remaining_time":0.213273235},
{"learn":[3.685491894],"iteration":620,"passed_time":0.3483949502,"remaining_time":0.2126275139},
{"learn":[3.684328128],"iteration":621,"passed_time":0.3488130803,"remaining_time":0.2119796533},
{"learn":[3.680640153],"iteration":622,"passed_time":0.349293859,"remaining_time":0.2113704411},
{"learn":[3.678932783],"iteration":623,"passed_time":0.3497465183,"remaining_time":0.2107446969},
{"learn":[3.674167041],"iteration":624,"passed_time":0.3502456165,"remaining_time":0.2101473699},
{"learn":[3.672200976],"iteration":625,"passed_time":0.350730325,"remaining_time":0.2095417597},
{"learn":[3.670606604],"iteration":626,"passed_time":0.3511773645,"remaining_time":0.2089141259},
{"learn":[3.665506042],"iteration":627,"passed_time":0.3517159118,"remaining_time":0.2083412726},
{"learn":[3.664214007],"iteration":628,"passed_time":0.3521580713,"remaining_time":0.2077116764},
{"learn":[3.66261643],"iteration":629,"passed_time":0.352551682,"remaining_time":0.2070541624},
{"learn":[3.662118449],"iteration":630,"passed_time":0.3529170834,"remaining_time":0.2063809885},
{"learn":[3.660871366],"iteration":631,"passed_time":0.3533290436,"remaining_time":0.2057358988},
{"learn":[3.656695243],"iteration":632,"passed_time":0.3537559236,"remaining_time":0.2051001958},
{"learn":[3.654497801],"iteration":633,"passed_time":0.3541806335,"remaining_time":0.2044638989},
{"learn":[3.654189134],"iteration":634,"passed_time":0.3546857616,"remaining_time":0.2038744929},
{"learn":[3.653957699],"iteration":635,"passed_time":0.3551375509,"remaining_time":0.2032548247},
{"learn":[3.651920725],"iteration":636,"passed_time":0.3555889103,"remaining_time":0.2026354387},
{"learn":[3.65106705],"iteration":637,"passed_time":0.3560320798,"remaining_time":0.2020119324},
{"learn":[3.650612844],"iteration":638,"passed_time":0.3564265305,"remaining_time":0.2013614671},
{"learn":[3.649884732],"iteration":639,"passed_time":0.3568321809,"remaining_time":0.2007181018},
{"learn":[3.646276182],"iteration":640,"passed_time":0.3572398413,"remaining_time":0.2000766038},
{"learn":[3.645808194],"iteration":641,"passed_time":0.3576355019,"remaining_time":0.1994291428},
{"learn":[3.645042989],"iteration":642,"passed_time":0.358057352,"remaining_time":0.1987970057},
{"learn":[3.639864499],"iteration":643,"passed_time":0.3584573125,"remaining_time":0.1981534212},
{"learn":[3.637318478],"iteration":644,"passed_time":0.3588937422,"remaining_time":0.1975306643},
{"learn":[3.636344905],"iteration":645,"passed_time":0.3593187422,"remaining_time":0.1969022209},
{"learn":[3.634754643],"iteration":646,"passed_time":0.3597353623,"remaining_time":0.1962698345},
{"learn":[3.630724975],"iteration":647,"passed_time":0.3601463226,"remaining_time":0.1956350394},
{"learn":[3.629408252],"iteration":648,"passed_time":0.3605349734,"remaining_time":0.1949888685},
{"learn":[3.62790646],"iteration":649,"passed_time":0.360935164,"remaining_time":0.1943497037},
{"learn":[3.627388973],"iteration":650,"passed_time":0.3613458543,"remaining_time":0.1937169019},
{"learn":[3.625163557],"iteration":651,"passed_time":0.3617920637,"remaining_time":0.1931037395},
{"learn":[3.623701985],"iteration":652,"passed_time":0.3631931106,"remaining_time":0.192998483},
{"learn":[3.622342639],"iteration":653,"passed_time":0.3636820391,"remaining_time":0.1924067057},
{"learn":[3.621130639],"iteration":654,"passed_time":0.3641440882,"remaining_time":0.1918010846},
{"learn":[3.619125665],"iteration":655,"passed_time":0.3646001474,"remaining_time":0.1911927602},
{"learn":[3.618878783],"iteration":656,"passed_time":0.3650276473,"remaining_time":0.1905699894},
{"learn":[3.616207429],"iteration":657,"passed_time":0.365506256,"remaining_time":0.1899743762},
{"learn":[3.61206486],"iteration":658,"passed_time":0.3659460856,"remaining_time":0.1893590519},
{"learn":[3.611955873],"iteration":659,"passed_time":0.3663214267,"remaining_time":0.188711038},
{"learn":[3.610713743],"iteration":660,"passed_time":0.3667160974,"remaining_time":0.1880737625},
{"learn":[3.610044025],"iteration":661,"passed_time":0.3671096581,"remaining_time":0.1874366532},
{"learn":[3.607342669],"iteration":662,"passed_time":0.3675123486,"remaining_time":0.1868049193},
{"learn":[3.602510618],"iteration":663,"passed_time":0.3679783276,"remaining_time":0.1862059007},
{"learn":[3.600492392],"iteration":664,"passed_time":0.3684496165,"remaining_time":0.1856099572},
{"learn":[3.597171065],"iteration":665,"passed_time":0.3689378649,"remaining_time":0.1850228932},
{"learn":[3.594358798],"iteration":666,"passed_time":0.3704023603,"remaining_time":0.1849235172},
{"learn":[3.593945251],"iteration":667,"passed_time":0.3709634871,"remaining_time":0.1843710744},
{"learn":[3.593607748],"iteration":668,"passed_time":0.3714076566,"remaining_time":0.1837607389},
{"learn":[3.592238714],"iteration":669,"passed_time":0.3718268867,"remaining_time":0.1831386158},
{"learn":[3.590144654],"iteration":670,"passed_time":0.3722498467,"remaining_time":0.1825189263},
{"learn":[3.587151536],"iteration":671,"passed_time":0.3726457173,"remaining_time":0.1818866001},
{"learn":[3.586070865],"iteration":672,"passed_time":0.3730334882,"remaining_time":0.1812510411},
{"learn":[3.585102746],"iteration":673,"passed_time":0.3734326188,"remaining_time":0.1806217117},
{"learn":[3.584362847],"iteration":674,"passed_time":0.3738401591,"remaining_time":0.1799971137},
{"learn":[3.581407561],"iteration":675,"passed_time":0.3742295299,"remaining_time":0.1793644493},
{"learn":[3.57919422],"iteration":676,"passed_time":0.3746172608,"remaining_time":0.1787317212},
{"learn":[3.577632204],"iteration":677,"passed_time":0.375032961,"remaining_time":0.1781129992},
{"learn":[3.573911195],"iteration":678,"passed_time":0.3754309816,"remaining_time":0.1774865171},
{"learn":[3.573408216],"iteration":679,"passed_time":0.3760165577,"remaining_time":0.1769489683},
{"learn":[3.571076482],"iteration":680,"passed_time":0.3764616472,"remaining_time":0.1763454706},
{"learn":[3.568177107],"iteration":681,"passed_time":0.3775842907,"remaining_time":0.1760583643},
{"learn":[3.564824621],"iteration":682,"passed_time":0.3782367653,"remaining_time":0.1755505924},
{"learn":[3.562475026],"iteration":683,"passed_time":0.3788716503,"remaining_time":0.1750342712},
{"learn":[3.561226889],"iteration":684,"passed_time":0.3794679362,"remaining_time":0.1744998539},
{"learn":[3.559383467],"iteration":685,"passed_time":0.3799708443,"remaining_time":0.1739225147},
{"learn":[3.555209766],"iteration":686,"passed_time":0.380451073,"remaining_time":0.1733350594},
{"learn":[3.55345383],"iteration":687,"passed_time":0.380871873,"remaining_time":0.1727209657},
{"learn":[3.552300968],"iteration":688,"passed_time":0.3813864209,"remaining_time":0.1721497488},
{"learn":[3.551253986],"iteration":689,"passed_time":0.3818331703,"remaining_time":0.1715482359},
{"learn":[3.549807725],"iteration":690,"passed_time":0.3823750875,"remaining_time":0.170989728},
{"learn":[3.547992926],"iteration":691,"passed_time":0.3829092349,"remaining_time":0.1704278098},
{"learn":[3.545438607],"iteration":692,"passed_time":0.38353835,"remaining_time":0.1699080425},
{"learn":[3.543313763],"iteration":693,"passed_time":0.3839870694,"remaining_time":0.1693084197},
{"learn":[3.542962896],"iteration":694,"passed_time":0.3843928899,"remaining_time":0.1686904049},
{"learn":[3.539800465],"iteration":695,"passed_time":0.3848890881,"remaining_time":0.1681124753},
{"learn":[3.53953187],"iteration":696,"passed_time":0.3852493296,"remaining_time":0.167475677},
{"learn":[3.536332425],"iteration":697,"passed_time":0.3857631075,"remaining_time":0.1669061009},
{"learn":[3.534993327],"iteration":698,"passed_time":0.3862171668,"remaining_time":0.1663109688},
{"learn":[3.531637011],"iteration":699,"passed_time":0.3866442467,"remaining_time":0.1657046771},
{"learn":[3.531040284],"iteration":700,"passed_time":0.3870703966,"remaining_time":0.1650985001},
{"learn":[3.529973872],"iteration":701,"passed_time":0.3874908667,"remaining_time":0.1644904249},
{"learn":[3.527325183],"iteration":702,"passed_time":0.3879292063,"remaining_time":0.1638904328},
{"learn":[3.527200815],"iteration":703,"passed_time":0.3884458641,"remaining_time":0.1633238292},
{"learn":[3.523459911],"iteration":704,"passed_time":0.3889008334,"remaining_time":0.1627315544},
{"learn":[3.522729934],"iteration":705,"passed_time":0.3893792821,"remaining_time":0.1621494461},
{"learn":[3.522260582],"iteration":706,"passed_time":0.3898678405,"remaining_time":0.1615718208},
{"learn":[3.518641591],"iteration":707,"passed_time":0.3903598489,"remaining_time":0.1609958699},
{"learn":[3.516856405],"iteration":708,"passed_time":0.3907711992,"remaining_time":0.1603870507},
{"learn":[3.515083413],"iteration":709,"passed_time":0.3917552059,"remaining_time":0.1600126898},
{"learn":[3.514671214],"iteration":710,"passed_time":0.3922417144,"remaining_time":0.1594343959},
{"learn":[3.512617621],"iteration":711,"passed_time":0.3926887239,"remaining_time":0.1588403827},
{"learn":[3.510747971],"iteration":712,"passed_time":0.3931535829,"remaining_time":0.1582539668},
{"learn":[3.508149266],"iteration":713,"passed_time":0.3936022223,"remaining_time":0.1576613944},
{"learn":[3.504557165],"iteration":714,"passed_time":0.394078901,"remaining_time":0.1570804011},
{"learn":[3.501367208],"iteration":715,"passed_time":0.3945959488,"remaining_time":0.1565157115},
{"learn":[3.497593362],"iteration":716,"passed_time":0.3950316285,"remaining_time":0.1559190389},
{"learn":[3.496291169],"iteration":717,"passed_time":0.3955932953,"remaining_time":0.155372297},
{"learn":[3.49330374],"iteration":718,"passed_time":0.3959937258,"remaining_time":0.1547624992},
{"learn":[3.490044385],"iteration":719,"passed_time":0.396407566,"remaining_time":0.1541584979},
{"learn":[3.488891789],"iteration":720,"passed_time":0.3967688275,"remaining_time":0.1535346781},
{"learn":[3.486869081],"iteration":721,"passed_time":0.397127399,"remaining_time":0.1529105498},
{"learn":[3.486303638],"iteration":722,"passed_time":0.3974886405,"remaining_time":0.152288179},
{"learn":[3.486035862],"iteration":723,"passed_time":0.3978675416,"remaining_time":0.1516732617},
{"learn":[3.482668951],"iteration":724,"passed_time":0.3982365528,"remaining_time":0.1510552442},
{"learn":[3.47820549],"iteration":725,"passed_time":0.3985996243,"remaining_time":0.1504356709},
{"learn":[3.474392283],"iteration":726,"passed_time":0.3989733454,"remaining_time":0.1498208023},
{"learn":[3.472268163],"iteration":727,"passed_time":0.3993441367,"remaining_time":0.1492055016},
{"learn":[3.471209164],"iteration":728,"passed_time":0.3997567869,"remaining_time":0.1486064325},
{"learn":[3.470049971],"iteration":729,"passed_time":0.4001731571,"remaining_time":0.1480092499},
{"learn":[3.469078654],"iteration":730,"passed_time":0.4005699777,"remaining_time":0.147405368},
{"learn":[3.468643292],"iteration":731,"passed_time":0.4009624784,"remaining_time":0.1468004703},
{"learn":[3.468134848],"iteration":732,"passed_time":0.4013331997,"remaining_time":0.1461882187},
{"learn":[3.467820182],"iteration":733,"passed_time":0.4016890113,"remaining_time":0.1455712221},
{"learn":[3.465776156],"iteration":734,"passed_time":0.4020473728,"remaining_time":0.1449558555},
{"learn":[3.463037608],"iteration":735,"passed_time":0.4024027844,"remaining_time":0.1443401292},
{"learn":[3.45965637],"iteration":736,"passed_time":0.402758146,"remaining_time":0.1437250915},
{"learn":[3.457275091],"iteration":737,"passed_time":0.4031460469,"remaining_time":0.1431223093},
{"learn":[3.455522955],"iteration":738,"passed_time":0.4035299878,"remaining_time":0.1425187102},
{"learn":[3.451270508],"iteration":739,"passed_time":0.4039423381,"remaining_time":0.1419256863},
{"learn":[3.450978947],"iteration":740,"passed_time":0.4043627181,"remaining_time":0.1413359568},
{"learn":[3.450608492],"iteration":741,"passed_time":0.4047980378,"remaining_time":0.1407518784},
{"learn":[3.448122004],"iteration":742,"passed_time":0.4053647945,"remaining_time":0.1402136638},
{"learn":[3.445646714],"iteration":743,"passed_time":0.4058033141,"remaining_time":0.1396312479},
{"learn":[3.44411263],"iteration":744,"passed_time":0.4062394438,"remaining_time":0.1390484002},
{"learn":[3.443264164],"iteration":745,"passed_time":0.4066585539,"remaining_time":0.1384601511},
{"learn":[3.439521363],"iteration":746,"passed_time":0.4070743341,"remaining_time":0.1378712269},
{"learn":[3.436809225],"iteration":747,"passed_time":0.4074613749,"remaining_time":0.1372730835},
{"learn":[3.435509465],"iteration":748,"passed_time":0.4079347037,"remaining_time":0.1367044201},
{"learn":[3.434450277],"iteration":749,"passed_time":0.4083567538,"remaining_time":0.1361189179},
{"learn":[3.431786753],"iteration":750,"passed_time":0.4087864236,"remaining_time":0.1355363775},
{"learn":[3.430150302],"iteration":751,"passed_time":0.4091450952,"remaining_time":0.1349308293},
{"learn":[3.42696281],"iteration":752,"passed_time":0.4094976368,"remaining_time":0.134323926},
{"learn":[3.426870334],"iteration":753,"passed_time":0.4098543584,"remaining_time":0.1337190612},
{"learn":[3.425200309],"iteration":754,"passed_time":0.4102226997,"remaining_time":0.1331186244},
{"learn":[3.423383783],"iteration":755,"passed_time":0.4106055607,"remaining_time":0.1325234878},
{"learn":[3.422752979],"iteration":756,"passed_time":0.4109943715,"remaining_time":0.131930822},
{"learn":[3.420845924],"iteration":757,"passed_time":0.4113766824,"remaining_time":0.1313366189},
{"learn":[3.418917862],"iteration":758,"passed_time":0.4117428638,"remaining_time":0.1307378527},
{"learn":[3.417095735],"iteration":759,"passed_time":0.4121348745,"remaining_time":0.1301478551},
{"learn":[3.414391848],"iteration":760,"passed_time":0.4125595845,"remaining_time":0.1295686474},
{"learn":[3.41426711],"iteration":761,"passed_time":0.4129507253,"remaining_time":0.1289793604},
{"learn":[3.411976013],"iteration":762,"passed_time":0.4133157066,"remaining_time":0.1283824672},
{"learn":[3.408614844],"iteration":763,"passed_time":0.4137123273,"remaining_time":0.1277959545},
{"learn":[3.407906721],"iteration":764,"passed_time":0.4140834885,"remaining_time":0.1272021174},
{"learn":[3.407494015],"iteration":765,"passed_time":0.41444368,"remaining_time":0.1266055106},
{"learn":[3.406287128],"iteration":766,"passed_time":0.4148330508,"remaining_time":0.1260183844},
{"learn":[3.404600442],"iteration":767,"passed_time":0.4152240016,"remaining_time":0.1254322505},
{"learn":[3.404012662],"iteration":768,"passed_time":0.4155966428,"remaining_time":0.1248411242},
{"learn":[3.400398762],"iteration":769,"passed_time":0.4159897135,"remaining_time":0.1242566677},
{"learn":[3.399737714],"iteration":770,"passed_time":0.4163843241,"remaining_time":0.123673165},
{"learn":[3.399185251],"iteration":771,"passed_time":0.4167851247,"remaining_time":0.1230919798},
{"learn":[3.397245411],"iteration":772,"passed_time":0.4172110946,"remaining_time":0.1225186526},
{"learn":[3.396229831],"iteration":773,"passed_time":0.4175807359,"remaining_time":0.1219292588},
{"learn":[3.394002836],"iteration":774,"passed_time":0.4179751066,"remaining_time":0.1213476116},
{"learn":[3.389617243],"iteration":775,"passed_time":0.418380647,"remaining_time":0.1207696713},
{"learn":[3.385426488],"iteration":776,"passed_time":0.4188795252,"remaining_time":0.1202189628},
{"learn":[3.385072258],"iteration":777,"passed_time":0.419310975,"remaining_time":0.1196491471},
{"learn":[3.383842366],"iteration":778,"passed_time":0.4197427348,"remaining_time":0.1190797746},
{"learn":[3.380110746],"iteration":779,"passed_time":0.4201963641,"remaining_time":0.1185169232},
{"learn":[3.378595218],"iteration":780,"passed_time":0.4205977246,"remaining_time":0.1179396949},
{"learn":[3.377371219],"iteration":781,"passed_time":0.4210926329,"remaining_time":0.1173889949},
{"learn":[3.375814782],"iteration":782,"passed_time":0.4215765415,"remaining_time":0.1168353889},
{"learn":[3.374195887],"iteration":783,"passed_time":0.4219675523,"remaining_time":0.1162563664},
{"learn":[3.373704309],"iteration":784,"passed_time":0.4224744403,"remaining_time":0.1157095601},
{"learn":[3.372971757],"iteration":785,"passed_time":0.422867331,"remaining_time":0.1151318179},
{"learn":[3.371565136],"iteration":786,"passed_time":0.4232447621,"remaining_time":0.1145503613},
{"learn":[3.3700309],"iteration":787,"passed_time":0.4236143734,"remaining_time":0.1139673187},
{"learn":[3.368186663],"iteration":788,"passed_time":0.4239884845,"remaining_time":0.1133860206},
{"learn":[3.366710398],"iteration":789,"passed_time":0.4243671456,"remaining_time":0.1128064564},
{"learn":[3.364598042],"iteration":790,"passed_time":0.424729117,"remaining_time":0.1122229905},
{"learn":[3.36348442],"iteration":791,"passed_time":0.4251039682,"remaining_time":0.1116434664},
{"learn":[3.362001759],"iteration":792,"passed_time":0.4255642273,"remaining_time":0.1110867529},
{"learn":[3.361580401],"iteration":793,"passed_time":0.4259546381,"remaining_time":0.1105121605},
{"learn":[3.359543675],"iteration":794,"passed_time":0.4263567886,"remaining_time":0.1099410587},
{"learn":[3.35766119],"iteration":795,"passed_time":0.42672027,"remaining_time":0.1093604712},
{"learn":[3.354592969],"iteration":796,"passed_time":0.42714142,"remaining_time":0.108795117},
{"learn":[3.350985986],"iteration":797,"passed_time":0.4275759798,"remaining_time":0.1082335187},
{"learn":[3.349589624],"iteration":798,"passed_time":0.4279630406,"remaining_time":0.1076602893},
{"learn":[3.349110856],"iteration":799,"passed_time":0.4283487215,"remaining_time":0.1070871804},
{"learn":[3.345315441],"iteration":800,"passed_time":0.4287352624,"remaining_time":0.1065147531},
{"learn":[3.34397474],"iteration":801,"passed_time":0.4291158634,"remaining_time":0.1059413229},
{"learn":[3.343800902],"iteration":802,"passed_time":0.4295036542,"remaining_time":0.1053701368},
{"learn":[3.342329465],"iteration":803,"passed_time":0.4299258443,"remaining_time":0.1048077929},
{"learn":[3.34220347],"iteration":804,"passed_time":0.4303261948,"remaining_time":0.1042405068},
{"learn":[3.341279219],"iteration":805,"passed_time":0.4307362051,"remaining_time":0.10367596},
{"learn":[3.337329521],"iteration":806,"passed_time":0.4311916144,"remaining_time":0.1031226537},
{"learn":[3.336708453],"iteration":807,"passed_time":0.4317518911,"remaining_time":0.1025945088},
{"learn":[3.333252703],"iteration":808,"passed_time":0.4322058704,"remaining_time":0.1020411882},
{"learn":[3.332186769],"iteration":809,"passed_time":0.4328035663,"remaining_time":0.1015218242},
{"learn":[3.330594851],"iteration":810,"passed_time":0.4333138042,"remaining_time":0.1009818853},
{"learn":[3.327867442],"iteration":811,"passed_time":0.4338180523,"remaining_time":0.1004406328},
{"learn":[3.327563111],"iteration":812,"passed_time":0.4343232204,"remaining_time":0.09989968292},
{"learn":[3.326308994],"iteration":813,"passed_time":0.4347832195,"remaining_time":0.09934849979},
{"learn":[3.326249879],"iteration":814,"passed_time":0.4352064195,"remaining_time":0.09878918726},
{"learn":[3.322336238],"iteration":815,"passed_time":0.4355861706,"remaining_time":0.09822041101},
{"learn":[3.320491154],"iteration":816,"passed_time":0.435950332,"remaining_time":0.09764860557},
{"learn":[3.320434271],"iteration":817,"passed_time":0.4363043836,"remaining_time":0.09707505845},
{"learn":[3.319609638],"iteration":818,"passed_time":0.436666865,"remaining_time":0.09650391034},
{"learn":[3.316182682],"iteration":819,"passed_time":0.4370287865,"remaining_time":0.09593314825},
{"learn":[3.313126612],"iteration":820,"passed_time":0.4374225272,"remaining_time":0.09536983236},
{"learn":[3.311222803],"iteration":821,"passed_time":0.4378750165,"remaining_time":0.09481965077},
{"learn":[3.309627335],"iteration":822,"passed_time":0.4382804669,"remaining_time":0.09425959009},
{"learn":[3.307974895],"iteration":823,"passed_time":0.4386472483,"remaining_time":0.09369164526},
{"learn":[3.307321505],"iteration":824,"passed_time":0.4390102797,"remaining_time":0.09312339266},
{"learn":[3.306759087],"iteration":825,"passed_time":0.4393840708,"remaining_time":0.09255790354},
{"learn":[3.30484037],"iteration":826,"passed_time":0.4397611719,"remaining_time":0.09199357043},
{"learn":[3.30201994],"iteration":827,"passed_time":0.4401560526,"remaining_time":0.09143338291},
{"learn":[3.299302297],"iteration":828,"passed_time":0.4405386136,"remaining_time":0.09087105298},
{"learn":[3.298132671],"iteration":829,"passed_time":0.4409331743,"remaining_time":0.090311614},
{"learn":[3.296976183],"iteration":830,"passed_time":0.4413356147,"remaining_time":0.08975417436},
{"learn":[3.293144745],"iteration":831,"passed_time":0.4417140958,"remaining_time":0.08919226935},
{"learn":[3.290284404],"iteration":832,"passed_time":0.442086957,"remaining_time":0.08862967805},
{"learn":[3.288285745],"iteration":833,"passed_time":0.4424819277,"remaining_time":0.08807194244},
{"learn":[3.286662667],"iteration":834,"passed_time":0.4428872981,"remaining_time":0.08751665172},
{"learn":[3.285692682],"iteration":835,"passed_time":0.4432785789,"remaining_time":0.08695895566},
{"learn":[3.284565611],"iteration":836,"passed_time":0.4436482501,"remaining_time":0.08639744895},
{"learn":[3.283897383],"iteration":837,"passed_time":0.44407643,"remaining_time":0.08584771081},
{"learn":[3.280712855],"iteration":838,"passed_time":0.4444863603,"remaining_time":0.08529476044},
{"learn":[3.280468341],"iteration":839,"passed_time":0.4448620914,"remaining_time":0.08473563647},
{"learn":[3.277814895],"iteration":840,"passed_time":0.4452766417,"remaining_time":0.08418428778},
{"learn":[3.276316385],"iteration":841,"passed_time":0.4456672324,"remaining_time":0.08362876808},
{"learn":[3.27557063],"iteration":842,"passed_time":0.4461710305,"remaining_time":0.08309472336},
{"learn":[3.27499628],"iteration":843,"passed_time":0.4468744739,"remaining_time":0.08259765158},
{"learn":[3.273569958],"iteration":844,"passed_time":0.4473808019,"remaining_time":0.08206393409},
{"learn":[3.269665595],"iteration":845,"passed_time":0.4479394788,"remaining_time":0.08153981055},
{"learn":[3.267984685],"iteration":846,"passed_time":0.4484571165,"remaining_time":0.08100819224},
{"learn":[3.267702508],"iteration":847,"passed_time":0.4489659845,"remaining_time":0.08047503496},
{"learn":[3.266671924],"iteration":848,"passed_time":0.4496397086,"remaining_time":0.07997125559},
{"learn":[3.265359825],"iteration":849,"passed_time":0.4500626086,"remaining_time":0.07942281328},
{"learn":[3.2618983],"iteration":850,"passed_time":0.4504508894,"remaining_time":0.07886860461},
{"learn":[3.260456253],"iteration":851,"passed_time":0.4508248306,"remaining_time":0.07831229452},
{"learn":[3.258389147],"iteration":852,"passed_time":0.4512046116,"remaining_time":0.07775741842},
{"learn":[3.258108469],"iteration":853,"passed_time":0.4516143319,"remaining_time":0.0772080708},
{"learn":[3.256424936],"iteration":854,"passed_time":0.4520145325,"remaining_time":0.07665743533},
{"learn":[3.254817983],"iteration":855,"passed_time":0.4524105531,"remaining_time":0.07610644819},
{"learn":[3.253898449],"iteration":856,"passed_time":0.4528082737,"remaining_time":0.07555610635},
{"learn":[3.253023652],"iteration":857,"passed_time":0.4531941646,"remaining_time":0.07500416244},
{"learn":[3.252845542],"iteration":858,"passed_time":0.4535723257,"remaining_time":0.07445133635},
{"learn":[3.252316026],"iteration":859,"passed_time":0.4539320772,"remaining_time":0.07389591954},
{"learn":[3.24975301],"iteration":860,"passed_time":0.4543080283,"remaining_time":0.07334357252},
{"learn":[3.249151075],"iteration":861,"passed_time":0.4546725497,"remaining_time":0.07278980494},
{"learn":[3.246257135],"iteration":862,"passed_time":0.4550439409,"remaining_time":0.07223756652},
{"learn":[3.243826471],"iteration":863,"passed_time":0.4554246819,"remaining_time":0.07168721845},
{"learn":[3.243190653],"iteration":864,"passed_time":0.4557953532,"remaining_time":0.07113569096},
{"learn":[3.24008797],"iteration":865,"passed_time":0.4561770942,"remaining_time":0.07058629402},
{"learn":[3.240036811],"iteration":866,"passed_time":0.4567596904,"remaining_time":0.07006809553},
{"learn":[3.238676314],"iteration":867,"passed_time":0.4572149996,"remaining_time":0.06953039165},
{"learn":[3.237848782],"iteration":868,"passed_time":0.4576764987,"remaining_time":0.06899381051},
{"learn":[3.236405498],"iteration":869,"passed_time":0.4580717994,"remaining_time":0.06844751026},
{"learn":[3.233378068],"iteration":870,"passed_time":0.4584796698,"remaining_time":0.06790341837},
{"learn":[3.233169169],"iteration":871,"passed_time":0.4589983275,"remaining_time":0.06737590129},
{"learn":[3.232434885],"iteration":872,"passed_time":0.4595050156,"remaining_time":0.0668466632},
{"learn":[3.229978115],"iteration":873,"passed_time":0.4600216533,"remaining_time":0.06631891112},
{"learn":[3.229648848],"iteration":874,"passed_time":0.4605197016,"remaining_time":0.0657885288},
{"learn":[3.227208761],"iteration":875,"passed_time":0.4610066601,"remaining_time":0.06525665051},
{"learn":[3.226258869],"iteration":876,"passed_time":0.4614576294,"remaining_time":0.06471982716},
{"learn":[3.225331995],"iteration":877,"passed_time":0.4619220385,"remaining_time":0.06418506685},
{"learn":[3.221968268],"iteration":878,"passed_time":0.4624451361,"remaining_time":0.06365854547},
{"learn":[3.221166317],"iteration":879,"passed_time":0.4628481466,"remaining_time":0.06311565635},
{"learn":[3.220047503],"iteration":880,"passed_time":0.4632293176,"remaining_time":0.06257013484},
{"learn":[3.21982781],"iteration":881,"passed_time":0.4635794293,"remaining_time":0.06202083068},
{"learn":[3.216693405],"iteration":882,"passed_time":0.4639424507,"remaining_time":0.06147368826},
{"learn":[3.214798761],"iteration":883,"passed_time":0.4643264917,"remaining_time":0.06092972062},
{"learn":[3.214395085],"iteration":884,"passed_time":0.464733702,"remaining_time":0.06038912512},
{"learn":[3.213470696],"iteration":885,"passed_time":0.4651546321,"remaining_time":0.059850596},
{"learn":[3.211595017],"iteration":886,"passed_time":0.4655947317,"remaining_time":0.05931477416},
{"learn":[3.210965255],"iteration":887,"passed_time":0.4660135418,"remaining_time":0.05877648275},
{"learn":[3.209413583],"iteration":888,"passed_time":0.4665166199,"remaining_time":0.05824898179},
{"learn":[3.208331683],"iteration":889,"passed_time":0.4669175705,"remaining_time":0.0577089132},
{"learn":[3.207110711],"iteration":890,"passed_time":0.4672985215,"remaining_time":0.05716671026},
{"learn":[3.204519413],"iteration":891,"passed_time":0.4677147716,"remaining_time":0.05662914275},
{"learn":[3.201421296],"iteration":892,"passed_time":0.4682015201,"remaining_time":0.05610029412},
{"learn":[3.200691259],"iteration":893,"passed_time":0.4686680291,"remaining_time":0.05556913992},
{"learn":[3.200485067],"iteration":894,"passed_time":0.4691069587,"remaining_time":0.0550348946},
{"learn":[3.197467568],"iteration":895,"passed_time":0.469517819,"remaining_time":0.05449760399},
{"learn":[3.195838544],"iteration":896,"passed_time":0.470026567,"remaining_time":0.05397183545},
{"learn":[3.195671746],"iteration":897,"passed_time":0.4709527851,"remaining_time":0.05349352348},
{"learn":[3.194213094],"iteration":898,"passed_time":0.4715145019,"remaining_time":0.05297326439},
{"learn":[3.192884691],"iteration":899,"passed_time":0.4720403294,"remaining_time":0.05244892549},
{"learn":[3.188364239],"iteration":900,"passed_time":0.4725372677,"remaining_time":0.05192140899},
{"learn":[3.185219478],"iteration":901,"passed_time":0.4730506856,"remaining_time":0.05139575076},
{"learn":[3.184120387],"iteration":902,"passed_time":0.4736334818,"remaining_time":0.05087757224},
{"learn":[3.183725321],"iteration":903,"passed_time":0.4741490496,"remaining_time":0.05035211146},
{"learn":[3.181264554],"iteration":904,"passed_time":0.4747090064,"remaining_time":0.04983133216},
{"learn":[3.180741589],"iteration":905,"passed_time":0.4752156144,"remaining_time":0.0493049313},
{"learn":[3.179782639],"iteration":906,"passed_time":0.4756791835,"remaining_time":0.04877416104},
{"learn":[3.176377564],"iteration":907,"passed_time":0.476163462,"remaining_time":0.04824563712},
{"learn":[3.174078182],"iteration":908,"passed_time":0.4766394208,"remaining_time":0.04771637766},
{"learn":[3.171242379],"iteration":909,"passed_time":0.4770430713,"remaining_time":0.04718008397},
{"learn":[3.170421012],"iteration":910,"passed_time":0.4775406395,"remaining_time":0.04665325677},
{"learn":[3.170087224],"iteration":911,"passed_time":0.4779913689,"remaining_time":0.04612197419},
{"learn":[3.167303059],"iteration":912,"passed_time":0.4784446982,"remaining_time":0.04559111582},
{"learn":[3.16705966],"iteration":913,"passed_time":0.4788245192,"remaining_time":0.04505351056},
{"learn":[3.165667683],"iteration":914,"passed_time":0.4793094577,"remaining_time":0.0445260152},
{"learn":[3.164689733],"iteration":915,"passed_time":0.4797019985,"remaining_time":0.0439901396},
{"learn":[3.163311455],"iteration":916,"passed_time":0.4800847994,"remaining_time":0.04345369504},
{"learn":[3.159425016],"iteration":917,"passed_time":0.4804752402,"remaining_time":0.04291826764},
{"learn":[3.159327058],"iteration":918,"passed_time":0.4808557312,"remaining_time":0.04238227881},
{"learn":[3.15819426],"iteration":919,"passed_time":0.4814652968,"remaining_time":0.04186654755},
{"learn":[3.157086603],"iteration":920,"passed_time":0.481881747,"remaining_time":0.04133404779},
{"learn":[3.153354154],"iteration":921,"passed_time":0.4822821875,"remaining_time":0.04080044536},
{"learn":[3.153261317],"iteration":922,"passed_time":0.4827135273,"remaining_time":0.04026970921},
{"learn":[3.153168454],"iteration":923,"passed_time":0.4831140879,"remaining_time":0.03973665658},
{"learn":[3.152080399],"iteration":924,"passed_time":0.4835691271,"remaining_time":0.0392083076},
{"learn":[3.151635144],"iteration":925,"passed_time":0.48429192,"remaining_time":0.03870151413},
{"learn":[3.147762655],"iteration":926,"passed_time":0.484760169,"remaining_time":0.03817420964},
{"learn":[3.147172317],"iteration":927,"passed_time":0.4852128583,"remaining_time":0.03764582521},
{"learn":[3.146254125],"iteration":928,"passed_time":0.4856635776,"remaining_time":0.03711745319},
{"learn":[3.144869828],"iteration":929,"passed_time":0.486749862,"remaining_time":0.03663708638},
{"learn":[3.143466218],"iteration":930,"passed_time":0.487385667,"remaining_time":0.03612203117},
{"learn":[3.141919643],"iteration":931,"passed_time":0.4879562735,"remaining_time":0.03560195987},
{"learn":[3.141054135],"iteration":932,"passed_time":0.4884465419,"remaining_time":0.03507601105},
{"learn":[3.139390417],"iteration":933,"passed_time":0.4888607821,"remaining_time":0.03454476619},
{"learn":[3.139025283],"iteration":934,"passed_time":0.4892553428,"remaining_time":0.03401240351},
{"learn":[3.137824183],"iteration":935,"passed_time":0.489710732,"remaining_time":0.0334844945},
{"learn":[3.135620453],"iteration":936,"passed_time":0.4901888107,"remaining_time":0.03295826582},
{"learn":[3.13443178],"iteration":937,"passed_time":0.4905795415,"remaining_time":0.03242636628},
{"learn":[3.132765713],"iteration":938,"passed_time":0.4909741622,"remaining_time":0.03189502012},
{"learn":[3.131434124],"iteration":939,"passed_time":0.4913390836,"remaining_time":0.03136206916},
{"learn":[3.128384262],"iteration":940,"passed_time":0.4917353642,"remaining_time":0.03083144154},
{"learn":[3.128120455],"iteration":941,"passed_time":0.4921303049,"remaining_time":0.03030101665},
{"learn":[3.126314615],"iteration":942,"passed_time":0.4925281655,"remaining_time":0.0297710556},
{"learn":[3.125409666],"iteration":943,"passed_time":0.4929215662,"remaining_time":0.02924110986},
{"learn":[3.123072589],"iteration":944,"passed_time":0.4933231867,"remaining_time":0.0287119315},
{"learn":[3.122921099],"iteration":945,"passed_time":0.4937788259,"remaining_time":0.02818610634},
{"learn":[3.122182662],"iteration":946,"passed_time":0.494200646,"remaining_time":0.02765853668},
{"learn":[3.120040951],"iteration":947,"passed_time":0.4945914867,"remaining_time":0.02712949083},
{"learn":[3.118767799],"iteration":948,"passed_time":0.4949721977,"remaining_time":0.02660019187},
{"learn":[3.118203218],"iteration":949,"passed_time":0.4953703183,"remaining_time":0.02607212202},
{"learn":[3.116343362],"iteration":950,"passed_time":0.4957866485,"remaining_time":0.0255452637},
{"learn":[3.11480829],"iteration":951,"passed_time":0.4961621196,"remaining_time":0.02501657746},
{"learn":[3.112607903],"iteration":952,"passed_time":0.4965790098,"remaining_time":0.02449025547},
{"learn":[3.111661241],"iteration":953,"passed_time":0.4969740405,"remaining_time":0.02396310887},
{"learn":[3.110249676],"iteration":954,"passed_time":0.4974009704,"remaining_time":0.02343774206},
{"learn":[3.107333579],"iteration":955,"passed_time":0.4978104407,"remaining_time":0.02291177761},
{"learn":[3.107149851],"iteration":956,"passed_time":0.4982113512,"remaining_time":0.022385672},
{"learn":[3.106867336],"iteration":957,"passed_time":0.498814467,"remaining_time":0.02186869271},
{"learn":[3.10364681],"iteration":958,"passed_time":0.4993693539,"remaining_time":0.02134947185},
{"learn":[3.102703811],"iteration":959,"passed_time":0.5003467108,"remaining_time":0.02084777962},
{"learn":[3.101469264],"iteration":960,"passed_time":0.50165081,"remaining_time":0.02035835753},
{"learn":[3.09863569],"iteration":961,"passed_time":0.502621927,"remaining_time":0.01985408859},
{"learn":[3.09645939],"iteration":962,"passed_time":0.5036193135,"remaining_time":0.0193498594},
{"learn":[3.096240186],"iteration":963,"passed_time":0.5044654135,"remaining_time":0.01883895735},
{"learn":[3.094838828],"iteration":964,"passed_time":0.5048761338,"remaining_time":0.01831156962},
{"learn":[3.094176802],"iteration":965,"passed_time":0.5052880841,"remaining_time":0.01778446673},
{"learn":[3.093182279],"iteration":966,"passed_time":0.5056927745,"remaining_time":0.01725735425},
{"learn":[3.090150687],"iteration":967,"passed_time":0.5061077247,"remaining_time":0.01673083387},
{"learn":[3.088612829],"iteration":968,"passed_time":0.5064902557,"remaining_time":0.01620350663},
{"learn":[3.087153684],"iteration":969,"passed_time":0.5069196155,"remaining_time":0.01567792625},
{"learn":[3.085866843],"iteration":970,"passed_time":0.5073379256,"remaining_time":0.01515221405},
{"learn":[3.082669094],"iteration":971,"passed_time":0.5077498359,"remaining_time":0.01462653848},
{"learn":[3.081047548],"iteration":972,"passed_time":0.508168696,"remaining_time":0.01410128961},
{"learn":[3.079684322],"iteration":973,"passed_time":0.508551317,"remaining_time":0.01357529183},
{"learn":[3.07613431],"iteration":974,"passed_time":0.5089772369,"remaining_time":0.01305069838},
{"learn":[3.074005935],"iteration":975,"passed_time":0.5093727776,"remaining_time":0.0125255601},
{"learn":[3.072988853],"iteration":976,"passed_time":0.5097657083,"remaining_time":0.01200062568},
{"learn":[3.072344268],"iteration":977,"passed_time":0.5101547691,"remaining_time":0.01147587415},
{"learn":[3.070654438],"iteration":978,"passed_time":0.5105485698,"remaining_time":0.0109515015},
{"learn":[3.069724506],"iteration":979,"passed_time":0.5109375706,"remaining_time":0.01042729736},
{"learn":[3.067763166],"iteration":980,"passed_time":0.5113695204,"remaining_time":0.009904200701},
{"learn":[3.066737893],"iteration":981,"passed_time":0.5117922104,"remaining_time":0.009381119947},
{"learn":[3.065248174],"iteration":982,"passed_time":0.5122311801,"remaining_time":0.008858524986},
{"learn":[3.063186837],"iteration":983,"passed_time":0.5127312082,"remaining_time":0.008337092817},
{"learn":[3.062880371],"iteration":984,"passed_time":0.5131874575,"remaining_time":0.007815037423},
{"learn":[3.061288645],"iteration":985,"passed_time":0.5136187773,"remaining_time":0.007292761543},
{"learn":[3.059970575],"iteration":986,"passed_time":0.5140173279,"remaining_time":0.006770238361},
{"learn":[3.059576341],"iteration":987,"passed_time":0.5144068687,"remaining_time":0.006247856704},
{"learn":[3.058175919],"iteration":988,"passed_time":0.5148089092,"remaining_time":0.005725882711},
{"learn":[3.056830702],"iteration":989,"passed_time":0.5152217294,"remaining_time":0.005204259893},
{"learn":[3.056336579],"iteration":990,"passed_time":0.5156370096,"remaining_time":0.004682878997},
{"learn":[3.055810414],"iteration":991,"passed_time":0.51604211,"remaining_time":0.00416162992},
{"learn":[3.055476518],"iteration":992,"passed_time":0.516425121,"remaining_time":0.00364045906},
{"learn":[3.053331734],"iteration":993,"passed_time":0.5168227916,"remaining_time":0.003119654678},
{"learn":[3.050890374],"iteration":994,"passed_time":0.5172535014,"remaining_time":0.002599263826},
{"learn":[3.04972623],"iteration":995,"passed_time":0.5176741315,"remaining_time":0.002079012576},
{"learn":[3.047217327],"iteration":996,"passed_time":0.5180719421,"remaining_time":0.001558892504},
{"learn":[3.047155483],"iteration":997,"passed_time":0.5184719426,"remaining_time":0.001039021929},
{"learn":[3.04430671],"iteration":998,"passed_time":0.5188831529,"remaining_time":0.0005194025555},
{"learn":[3.042664195],"iteration":999,"passed_time":0.5192904233,"remaining_time":0}
]}